{"http://cdn.adf.ly/static/image/blockquote_bg.png": {"documentURL": "http://www.adf.ly/", "parent": "http://cdn.adf.ly/static/css/core46.css", "url": "http://cdn.adf.ly/static/image/blockquote_bg.png", "isRoot": false, "priority": "Low", "found_index": 51, "request_id": "5550.73", "type": "Image", "children": [], "isLeaf": true}, "https://static.licdn.com/scds/concat/common/css?h=8lpissn6x7y2031ehsfug0tan": {"documentURL": "https://www.linkedin.com/cws/followcompany?companyIdentifier=5359353&counterPosition=none&original_referer=http%3A%2F%2Fwww.adf.ly%2F&token=&isFramed=false&lang=en_US&_ts=1496541619861.3257&xd_origin_host=http%3A%2F%2Fwww.adf.ly", "parent": "https://www.linkedin.com/cws/followcompany?companyIdentifier=5359353&counterPosition=none&original_referer=http%3A%2F%2Fwww.adf.ly%2F&token=&isFramed=false&lang=en_US&_ts=1496541619861.3257&xd_origin_host=http%3A%2F%2Fwww.adf.ly", "url": "https://static.licdn.com/scds/concat/common/css?h=8lpissn6x7y2031ehsfug0tan", "isRoot": false, "priority": "VeryLow", "found_index": 91, "request_id": "5550.127", "type": "Stylesheet", "children": [], "isLeaf": true}, "http://cdn.adf.ly/static/image/shrink_bg.png": {"documentURL": "http://www.adf.ly/", "parent": "http://cdn.adf.ly/static/css/core46.css", "url": "http://cdn.adf.ly/static/image/shrink_bg.png", "isRoot": false, "priority": "Low", "found_index": 35, "request_id": "5550.57", "type": "Image", "children": [], "isLeaf": true}, "http://cdn.adf.ly/static/js/spin.js": {"isRoot": false, "parent": "http://www.adf.ly/", "url": "http://cdn.adf.ly/static/js/spin.js", "priority": "High", "found_index": 16, "request_id": "5550.16", "type": "Script", "children": ["http://cdn.adf.ly/static/css/jquery-ui/ui-lightness/images/ui-bg_gloss-wave_35_f6a828_500x100.png"], "isLeaf": false, "documentURL": "http://www.adf.ly/"}, "http://cdn.adf.ly/static/image/shrink_button_icon.png": {"documentURL": "http://www.adf.ly/", "parent": "http://cdn.adf.ly/static/css/core46.css", "url": "http://cdn.adf.ly/static/image/shrink_button_icon.png", "isRoot": false, "priority": "Low", "found_index": 36, "request_id": "5550.58", "type": "Image", "children": [], "isLeaf": true}, "http://cdn.adf.ly/static/js/jquery.form.min.js": {"documentURL": "http://www.adf.ly/", "parent": "http://www.adf.ly/", "url": "http://cdn.adf.ly/static/js/jquery.form.min.js", "isRoot": false, "priority": "High", "found_index": 11, "request_id": "5550.11", "type": "Script", "children": [], "isLeaf": true}, "http://cdn.adf.ly/static/image/quote_photo_bg.png": {"documentURL": "http://www.adf.ly/", "parent": "http://cdn.adf.ly/static/css/core46.css", "url": "http://cdn.adf.ly/static/image/quote_photo_bg.png", "isRoot": false, "priority": "Low", "found_index": 49, "request_id": "5550.71", "type": "Image", "children": [], "isLeaf": true}, "http://cdn.adf.ly/static/image/links_clicked_bg.png": {"documentURL": "http://www.adf.ly/", "parent": "http://cdn.adf.ly/static/css/core46.css", "url": "http://cdn.adf.ly/static/image/links_clicked_bg.png", "isRoot": false, "priority": "Low", "found_index": 52, "request_id": "5550.74", "type": "Image", "children": [], "isLeaf": true}, "https://platform.linkedin.com/js/xdrpc.html?v=0.0.2000-RC8.59768-1429": {"documentURL": "https://platform.linkedin.com/js/xdrpc.html?v=0.0.2000-RC8.59768-1429", "parent": "https://platform.linkedin.com/js/secureAnonymousFramework?v=0.0.2000-RC8.59768-1429&lang=en_US", "url": "https://platform.linkedin.com/js/xdrpc.html?v=0.0.2000-RC8.59768-1429", "isRoot": false, "priority": "VeryLow", "found_index": 80, "request_id": "5550.110", "type": "Document", "children": ["https://www.linkedin.com/cws/followcompany?companyIdentifier=5359353&counterPosition=none&original_referer=http%3A%2F%2Fwww.adf.ly%2F&token=&isFramed=false&lang=en_US&_ts=1496541619861.3257&xd_origin_host=http%3A%2F%2Fwww.adf.ly"], "isLeaf": false}, "http://cdn.adf.ly/static/image/header.png": {"documentURL": "http://www.adf.ly/", "parent": "http://cdn.adf.ly/static/css/core46.css", "url": "http://cdn.adf.ly/static/image/header.png", "isRoot": false, "priority": "Low", "found_index": 31, "request_id": "5550.53", "type": "Image", "children": [], "isLeaf": true}, "https://www.linkedin.com/uas/js/anonymoususerspace": {"documentURL": "https://www.linkedin.com/cws/followcompany?companyIdentifier=5359353&counterPosition=none&original_referer=http%3A%2F%2Fwww.adf.ly%2F&token=&isFramed=false&lang=en_US&_ts=1496541619861.3257&xd_origin_host=http%3A%2F%2Fwww.adf.ly", "parent": "https://www.linkedin.com/cws/followcompany?companyIdentifier=5359353&counterPosition=none&original_referer=http%3A%2F%2Fwww.adf.ly%2F&token=&isFramed=false&lang=en_US&_ts=1496541619861.3257&xd_origin_host=http%3A%2F%2Fwww.adf.ly", "url": "https://www.linkedin.com/uas/js/anonymoususerspace", "isRoot": false, "priority": "VeryLow", "found_index": 89, "request_id": "5550.125", "type": "Script", "children": [], "isLeaf": true}, "https://bam.nr-data.net/1/92a411bc23?a=2344943,2334836&v=998.365d633&to=YlNSbUYAV0IFBhdaWVsZc0xHFVZcSwwNV1NNdV9XQBNWXQgAERxfW1JVQQ%3D%3D&rst=12720&ref=http://www.adf.ly/&ap=24&be=408&fe=11990&dc=2421&af=err,xhr&perf=%7B%22timing%22:%7B%22of%22:1496541609816,%22n%22:0,%22f%22:2,%22dn%22:2,%22dne%22:2,%22c%22:2,%22ce%22:2,%22rq%22:27,%22rp%22:212,%22rpe%22:375,%22dl%22:304,%22di%22:2829,%22ds%22:2829,%22de%22:3279,%22dc%22:12395,%22l%22:12397,%22le%22:12404%7D,%22navigation%22:%7B%7D%7D&at=ThRRGw4aREw%3D&jsonp=NREUM.setToken": {"documentURL": "http://www.adf.ly/", "parent": "https://js-agent.newrelic.com/nr-998.min.js", "url": "https://bam.nr-data.net/1/92a411bc23?a=2344943,2334836&v=998.365d633&to=YlNSbUYAV0IFBhdaWVsZc0xHFVZcSwwNV1NNdV9XQBNWXQgAERxfW1JVQQ%3D%3D&rst=12720&ref=http://www.adf.ly/&ap=24&be=408&fe=11990&dc=2421&af=err,xhr&perf=%7B%22timing%22:%7B%22of%22:1496541609816,%22n%22:0,%22f%22:2,%22dn%22:2,%22dne%22:2,%22c%22:2,%22ce%22:2,%22rq%22:27,%22rp%22:212,%22rpe%22:375,%22dl%22:304,%22di%22:2829,%22ds%22:2829,%22de%22:3279,%22dc%22:12395,%22l%22:12397,%22le%22:12404%7D,%22navigation%22:%7B%7D%7D&at=ThRRGw4aREw%3D&jsonp=NREUM.setToken", "isRoot": false, "priority": "Low", "found_index": 95, "request_id": "5550.140", "type": "Script", "children": [], "isLeaf": true}, "http://staticxx.facebook.com/connect/xd_arbiter/r/D6ZfFsLEB4F.js?version=42": {"documentURL": "http://staticxx.facebook.com/connect/xd_arbiter/r/D6ZfFsLEB4F.js?version=42", "parent": "http://connect.facebook.net/en_US/sdk.js", "url": "http://staticxx.facebook.com/connect/xd_arbiter/r/D6ZfFsLEB4F.js?version=42", "isRoot": false, "priority": "VeryLow", "found_index": 62, "request_id": "5550.88", "type": "Document", "children": [], "isLeaf": true}, "http://cdn.adf.ly/static/js/common.js": {"documentURL": "http://www.adf.ly/", "parent": "http://www.adf.ly/", "url": "http://cdn.adf.ly/static/js/common.js", "isRoot": false, "priority": "High", "found_index": 7, "request_id": "5550.7", "type": "Script", "children": [], "isLeaf": true}, "http://www.google-analytics.com/ga.js": {"documentURL": "http://www.adf.ly/", "parent": "http://www.adf.ly/", "url": "http://www.google-analytics.com/ga.js", "isRoot": false, "priority": "Medium", "found_index": 25, "request_id": "5550.29", "type": "Script", "children": [], "isLeaf": true}, "http://cdn.adf.ly/static/image/stats.png": {"documentURL": "http://www.adf.ly/", "parent": "http://cdn.adf.ly/static/css/core46.css", "url": "http://cdn.adf.ly/static/image/stats.png", "isRoot": false, "priority": "Low", "found_index": 46, "request_id": "5550.68", "type": "Image", "children": [], "isLeaf": true}, "http://cdn.adf.ly/static/css/jquery.ulightbox.css": {"documentURL": "http://www.adf.ly/", "parent": "http://www.adf.ly/", "url": "http://cdn.adf.ly/static/css/jquery.ulightbox.css", "isRoot": false, "priority": "VeryHigh", "found_index": 19, "request_id": "5550.19", "type": "Stylesheet", "children": [], "isLeaf": true}, "http://cdn.adf.ly/static/image/ft_paypal.png": {"documentURL": "http://www.adf.ly/", "parent": "http://cdn.adf.ly/static/css/core46.css", "url": "http://cdn.adf.ly/static/image/ft_paypal.png", "isRoot": false, "priority": "Low", "found_index": 57, "request_id": "5550.81", "type": "Image", "children": [], "isLeaf": true}, "https://static.licdn.com/scds/concat/common/js?h=a0jta68t22m53ctufp62mjb9b-3l5b0m8v4ywigyorwrawyorqp-1qxt69eezmfo5p7guan5m28k2-9ahtd75n2fngapkt47zxa83l4-6yo19j3zbvfkaftihaqj2wc8w-e34cdkc3cj077ikcayyyu2wpj-djvfw8en5rvj07kmioaklpk4z-el185lpi61t6smwdvp596sh6y-4ofin259c3rzrgxsz7haoevdt-1yevi40jf10exl64ba3pbm14t-84wiass0xmq0bsclerixvl4m0-cub2uboipu4ax82cvyddnnoea-1n8sluvsemdb4gb3xm7zgz652-8h350yj4rwtwp973benlp6pil-2v6nrp0wa0nlrkpmb32i62enx-9yapbb9c5ce3w0tjhqp8s1ben-be35lq69dqsbgl8h9t4bqpy08-avftajdh5oq2u6k2vaor3czdy-2r5gveucqe4lsolc3n0oljsn1-e9rsfv7b5gx0bk0tln31dx3sq-c8ha6zrgpgcni7poa5ctye7il-51dv6schthjydhvcv6rxvospp-b88qxy99s08xoes3weacd08uc-4805qyau5m6n9u7wprikb8gtg-bwrd332dvhbcfx9p9k3ge4w1v-5gedbbq7rksg5ypd5ruwisrah-diqd38xo23p6u922ihupn59iv-2swpl0141fhjbvotjp0vhbq5p": {"documentURL": "https://www.linkedin.com/cws/followcompany?companyIdentifier=5359353&counterPosition=none&original_referer=http%3A%2F%2Fwww.adf.ly%2F&token=&isFramed=false&lang=en_US&_ts=1496541619861.3257&xd_origin_host=http%3A%2F%2Fwww.adf.ly", "parent": "https://www.linkedin.com/cws/followcompany?companyIdentifier=5359353&counterPosition=none&original_referer=http%3A%2F%2Fwww.adf.ly%2F&token=&isFramed=false&lang=en_US&_ts=1496541619861.3257&xd_origin_host=http%3A%2F%2Fwww.adf.ly", "url": "https://static.licdn.com/scds/concat/common/js?h=a0jta68t22m53ctufp62mjb9b-3l5b0m8v4ywigyorwrawyorqp-1qxt69eezmfo5p7guan5m28k2-9ahtd75n2fngapkt47zxa83l4-6yo19j3zbvfkaftihaqj2wc8w-e34cdkc3cj077ikcayyyu2wpj-djvfw8en5rvj07kmioaklpk4z-el185lpi61t6smwdvp596sh6y-4ofin259c3rzrgxsz7haoevdt-1yevi40jf10exl64ba3pbm14t-84wiass0xmq0bsclerixvl4m0-cub2uboipu4ax82cvyddnnoea-1n8sluvsemdb4gb3xm7zgz652-8h350yj4rwtwp973benlp6pil-2v6nrp0wa0nlrkpmb32i62enx-9yapbb9c5ce3w0tjhqp8s1ben-be35lq69dqsbgl8h9t4bqpy08-avftajdh5oq2u6k2vaor3czdy-2r5gveucqe4lsolc3n0oljsn1-e9rsfv7b5gx0bk0tln31dx3sq-c8ha6zrgpgcni7poa5ctye7il-51dv6schthjydhvcv6rxvospp-b88qxy99s08xoes3weacd08uc-4805qyau5m6n9u7wprikb8gtg-bwrd332dvhbcfx9p9k3ge4w1v-5gedbbq7rksg5ypd5ruwisrah-diqd38xo23p6u922ihupn59iv-2swpl0141fhjbvotjp0vhbq5p", "isRoot": false, "priority": "VeryLow", "found_index": 90, "request_id": "5550.126", "type": "Script", "children": ["https://static.licdn.com/scds/common/u/images/apps/connect/sprites/sprite_connect_v15.png"], "isLeaf": false}, "http://cdn.adf.ly/static/image/register_bg.png": {"documentURL": "http://www.adf.ly/", "parent": "http://cdn.adf.ly/static/css/core46.css", "url": "http://cdn.adf.ly/static/image/register_bg.png", "isRoot": false, "priority": "Low", "found_index": 37, "request_id": "5550.59", "type": "Image", "children": [], "isLeaf": true}, "http://cdn.adf.ly/static/image/num_bg.png": {"documentURL": "http://www.adf.ly/", "parent": "http://cdn.adf.ly/static/css/core46.css", "url": "http://cdn.adf.ly/static/image/num_bg.png", "isRoot": false, "priority": "Low", "found_index": 53, "request_id": "5550.75", "type": "Image", "children": [], "isLeaf": true}, "http://www.adf.ly/": {"isRoot": true, "parent": null, "url": "http://www.adf.ly", "priority": "VeryHigh", "found_index": 1, "request_id": "5550.1", "type": "Document", "children": ["http://www.google-analytics.com/ga.js", "http://www.adf.ly/static/image/testimonials/monicacorrea_small.jpg", "http://cdn.adf.ly/static/js/index/index.js", "http://s7.addthis.com/js/300/addthis_widget.js", "http://platform.linkedin.com/in.js", "http://www.google.com/recaptcha/api/challenge?k=6LcmBQUTAAAAABRUqaI7Jt-bv9vr4Xpwh7MMVVW5", "http://cdn.adf.ly/static/js/jquery-ui-1.9m7.min.js", "http://cdn.adf.ly/static/js/ie6-warning.js", "http://cdn.adf.ly/static/js/home.js", "http://cdn.adf.ly/static/js/spin.js", "http://cdn.adf.ly/static/js/jquery.form.min.js", "http://cdn.adf.ly/static/js/chosen.jquery.min.js", "http://cdn.adf.ly/static/js/modernizr.js", "http://cdn.adf.ly/static/js/ZeroClipboard.js", "http://cdn.adf.ly/static/css/jquery.ulightbox.css", "http://cdn.adf.ly/static/js/jquery.ulightbox.js", "http://www.google.com/recaptcha/api/image?c=03AHJ_VusklXo3i4W1oVTV1_T7HfXCrtYSaTgY-TIJ2Rg-stiGU84z7wHlJKAE77gtTi443xpW20DKvHCFyo379t2SSSEsqZJOQXE0_5CtAoDuyk6I0vX_wG2nv_RoTm8RPgSYN5_xqP6hWEPohFplMKr8dvkKKnJbG3iLuqZYsFK6TkEMuUjnJISB6XLFU3zWfAGripVG0zFNMwELiotY8UtCvvjo8sMSnQ&th=,BfRX9NWweSjAM18tQ1a2tP-YFW-TcMTwAAAB6aAAAAS3awNj-xaxzfabbDAdRoS7PcfEJwaR7m5BEvu0Nm6eIst4ymEJkUcGyq8n4JwPptd-wjWVnlJEyA-tZPm8YzdhgLHjfhGUususM7Qh1SovD36nt8rpdzvSRiznoTNKdNiU1974mvG8hYI7mGXwavi73NW3idPuBf94M22eO_2o0atqdq7ERZoBbHxhe_qAI7FFGABePXUjoE4qy6q6bSwaNlSLQixu7jKxg7d2EAtuRcRLUeXashObkK-_p2dYBBfzTf_h_4-q2P7maqTzSamPVJEZcWfK81o7qBpgS74qeRPhM0CvulRatUHSpz4PBXG1y9LfvDw8g2bzKDMbSIzDT0GxJ6vYku8ldwd3RGCR9zQrLmsNBoUDcNB3Bfd6z4TZb0C_rYhT2wst1W70deoR7Fnwg3zKPT_91fuDT7HKW4JUjpSUotr0Bl0QWS8ihESyb05DlgXzFZRz_ZXdwB1IqRVG_tclx6J5JvylXftnTtIv8GMhTrjtZoEmRAwlgpu3IZxu7u01S5pLQoJGhxVuHahrIP17oHeTCt11UES3Z0H3kEHs5eS1mn6UeLs6ZSI9MeeHFyi-n3LrgDZF-xRjPhefLxDYOhpTrYSJ5kAog9CJTgWInD1zXVGTtMab8F7GfvtmEBtks99JscF1skBQBqG9NQDDbyZZ1SnDDbS4_gReo0C3RC3fsIcDNHc0cZ1AkYnQQPukf6ikkKEsJRpOjATqg4PzbZgO8F_gLK3cTz5Oq0Tli4WRwWSMWQFvw24dHWYt8YD474fQ2GriL3lTemAf53r7UiNOie2cpW2VtUqWm_x-q-1Iz4DcgZfepHnH2GXkpH4IwxmHREMXO4dS74CvJifFAfH57-qXgGlZ0sPQQebk9iFornGoVqXR1Gm7AWbQ_Ne55QmKIF8BI2ubSkX0F76dVrWA9jJg2wGmGj4b3BTOc9KbgQAtuKPyluZR97qLC-IU8aBTarKA2yOQMdc7s3QcU1B-mQKmJ8eb-5Qt4yMg1ayl7roETStjh1oiDACA5RZyO-CaUK7LLwG3OpLrMllCR0yk_2n8G3aCfxauRAblIboj3bpcq56ddyXgFeLeOedohWMec9AEKB-Tt4Ovxv_PFy1uG6TBt-5HN-7_EgxKJ6iPklgiH3cFpG0FpGJXI7fT", "http://www.google.com/recaptcha/api/image?c=03AHJ_VusklXo3i4W1oVTV1_T7HfXCrtYSaTgY-TIJ2Rg-stiGU84z7wHlJKAE77gtTi443xpW20DKvHCFyo379t2SSSEsqZJOQXE0_5CtAoDuyk6I0vX_wG2nv_RoTm8RPgSYN5_xqP6hWEPohFplMKr8dvkKKnJbG3iLuqZYsFK6TkEMuUjnJISB6XLFU3zWfAGripVG0zFNMwELiotY8UtCvvjo8sMSnQ&th=,YpNXk7KweSjAM18tQ1a2tP-YFW-TcMTwAAAB6aAAAAOXawNj-xaxzfabbDAdRoS7PcfEJwaR7m5BEvu0Nm6eIst4ymEJkUcGyq8n4JwPptd-wjWVnlJEyA-tZPm8YzdhgLHjfhGUususM7Qh1SovD36nt8rpdzvSRiznoTNKdNiU1974mvG8hYI7mGXwavi73NW3idPuBf94M22eO_2o0atqdq7ERZoBbHxhe_qAI7FFGABePXUjoE4qy6q6bSwaNlSLQixu7jKxg7d2EAtuRcRLUeXashObize_p2dYBBdRVLUgnnCZdPX5R1d9xcZE0y8dPkHOIEIjj4WltmgpUQarPBkTYsjAojJvOLwPgswQlGA7iXQFHPHW6oMrFtYPK1wSyr_Pv0vKgz_lVbfjtLdc5_lmFGdygwRrcOlYBYvHu0Tft-SoPZGrSA1VoKlkIBXxWn_KQ_0Da7Jb9BKyva_ykSzacdAfYqRhoUL3Eu9HjL2t-hoJkBpFoPIvHIxK7PwokD3iTihB71ERge8Z5RynAQbFzR-C1AZW9gdj_mowuX2cwgqy26tc6TOWh-FlwnZNq-m9tZnAkI6AZlIjUjkp_zqIXCbpwQIbS5oefEeeybBonk3tMCTNbahFF_ZjIHdZyohnBWAJQQiu1QcUdHqdvPP9yvm9IExYQogfpHHkepsn_PVsYCRnBKT-RtjJ4_xh0msJSkBj3mwI-whGa1TfTUjFMQNjnRv6SzewPzGG_wBCOUAZVSJrh-G69IqXWLT3rEoORqBhJecGV9_44chPSPciKynGhC01dmQgnBbjNQXfu_N_l4zlqU1FKeq0EHvX6q-fLak3SWZbens-S0f4KCl2iTeIJhBWcCSOvJ5mQX2H_Ry9CDDZuSRFBRWu_GHacl_AFrQB6OfioyZzmSBU2t9-b0kJTD_UDAJhrepm5LhQxVZFdZd1wUsZPKIFyR38Ql-AWrJoFEAyVlxvSho38nIfbkNG-wa1Q7Q8_I1HSsGxXtCYZ98FevijGB5Otpn5wnFYRwgPyggRrIGd0-0w2OwgLzdaJu0-Z_-bixRpcycMeTZKqje9Jryd76-69te8gjWal-rDsbB6vwnt2TsqBKt-N05XONA94N-NXg1KwDlLZEC-d4Fi66uhpkKo7icBxAi8H8koi35BJP2TFODH0ESOeRYDYFLF9FmNJui_tODibK8K", "https://js-agent.newrelic.com/nr-998.min.js", "http://www.google.com/recaptcha/api/img/red/help.gif", "http://www.google.com/recaptcha/api/img/red/audio.gif", "http://www.google.com/recaptcha/api/img/red/text.gif", "http://www.google.com/recaptcha/api/img/red/refresh.gif", "http://connect.facebook.net/en_US/sdk.js", "http://cdn.adf.ly/static/css/jquery.loadmask.css", "http://cdn.adf.ly/static/css/jquery-ui/ui-lightness/jquery-ui-1.8.16.custom.css", "http://cdn.adf.ly/static/js/jquery-1.7.1.min.js", "http://cdn.adf.ly/static/css/core46.css", "http://cdn.adf.ly/static/js/common.js", "http://cdn.adf.ly/static/js/jquery.browserdetect.min.js", "http://cdn.adf.ly/static/js/jquery.loadmask.min.js", "http://cdn.adf.ly/static/js/jquery.placeholder.min.js", "http://cdn.adf.ly/static/image/delete2.png"], "isLeaf": false, "documentURL": "http://www.adf.ly/"}, "http://s7.addthis.com/static/layers.ea0ccaf667d08a14f4c7.js": {"documentURL": "http://www.adf.ly/", "parent": "http://s7.addthis.com/js/300/addthis_widget.js", "url": "http://s7.addthis.com/static/layers.ea0ccaf667d08a14f4c7.js", "isRoot": false, "priority": "Low", "found_index": 79, "request_id": "5550.109", "type": "Script", "children": [], "isLeaf": true}, "http://www.google.com/recaptcha/api/img/red/audio.gif": {"documentURL": "http://www.adf.ly/", "parent": "http://www.adf.ly/", "url": "http://www.google.com/recaptcha/api/img/red/audio.gif", "isRoot": false, "priority": "Low", "found_index": 76, "request_id": "5550.106", "type": "Image", "children": [], "isLeaf": true}, "http://cdn.adf.ly/static/js/jquery-ui-1.9m7.min.js": {"documentURL": "http://www.adf.ly/", "parent": "http://www.adf.ly/", "url": "http://cdn.adf.ly/static/js/jquery-ui-1.9m7.min.js", "isRoot": false, "priority": "High", "found_index": 15, "request_id": "5550.15", "type": "Script", "children": [], "isLeaf": true}, "http://cdn.adf.ly/static/image/chosen-sprite.png": {"documentURL": "http://www.adf.ly/", "parent": "http://cdn.adf.ly/static/js/jquery-1.7.1.min.js", "url": "http://cdn.adf.ly/static/image/chosen-sprite.png", "isRoot": false, "priority": "Low", "found_index": 68, "request_id": "5550.98", "type": "Image", "children": [], "isLeaf": true}, "https://www.facebook.com/v2.0/plugins/like.php?action=like&app_id=399141353502152&channel=http%3A%2F%2Fstaticxx.facebook.com%2Fconnect%2Fxd_arbiter%2Fr%2FD6ZfFsLEB4F.js%3Fversion%3D42%23cb%3Df2e1767fdd9b89%26domain%3Dwww.adf.ly%26origin%3Dhttp%253A%252F%252Fwww.adf.ly%252Ff9943e9dc72f28%26relation%3Dparent.parent&container_width=0&href=https%3A%2F%2Fwww.facebook.com%2FFB_SLUG&layout=standard&locale=en_US&sdk=joey&share=true&show_faces=true&width=280": {"isRoot": false, "parent": "http://connect.facebook.net/en_US/sdk.js", "url": "https://www.facebook.com/v2.0/plugins/like.php?action=like&app_id=399141353502152&channel=http%3A%2F%2Fstaticxx.facebook.com%2Fconnect%2Fxd_arbiter%2Fr%2FD6ZfFsLEB4F.js%3Fversion%3D42%23cb%3Df2e1767fdd9b89%26domain%3Dwww.adf.ly%26origin%3Dhttp%253A%252F%252Fwww.adf.ly%252Ff9943e9dc72f28%26relation%3Dparent.parent&container_width=0&href=https%3A%2F%2Fwww.facebook.com%2FFB_SLUG&layout=standard&locale=en_US&sdk=joey&share=true&show_faces=true&width=280", "priority": "VeryLow", "found_index": 74, "request_id": "5550.104", "type": "Document", "children": ["https://static.xx.fbcdn.net/rsrc.php/v3/yD/r/FEppCFCt76d.png", "https://static.xx.fbcdn.net/rsrc.php/v3iSgH4/yb/l/en_US/RcW9ItWDVXf.js"], "isLeaf": false, "documentURL": "https://www.facebook.com/v2.0/plugins/like.php?action=like&app_id=399141353502152&channel=http%3A%2F%2Fstaticxx.facebook.com%2Fconnect%2Fxd_arbiter%2Fr%2FD6ZfFsLEB4F.js%3Fversion%3D42%23cb%3Df2e1767fdd9b89%26domain%3Dwww.adf.ly%26origin%3Dhttp%253A%252F%252Fwww.adf.ly%252Ff9943e9dc72f28%26relation%3Dparent.parent&container_width=0&href=https%3A%2F%2Fwww.facebook.com%2FFB_SLUG&layout=standard&locale=en_US&sdk=joey&share=true&show_faces=true&width=280"}, "http://www.google.com/recaptcha/api/js/recaptcha.js?_=1496541612855": {"documentURL": "http://www.adf.ly/", "parent": "http://cdn.adf.ly/static/js/jquery-1.7.1.min.js", "url": "http://www.google.com/recaptcha/api/js/recaptcha.js?_=1496541612855", "isRoot": false, "priority": "Low", "found_index": 70, "request_id": "5550.100", "type": "Script", "children": ["http://www.google.com/recaptcha/api/reload?c=03AHJ_VusklXo3i4W1oVTV1_T7HfXCrtYSaTgY-TIJ2Rg-stiGU84z7wHlJKAE77gtTi443xpW20DKvHCFyo379t2SSSEsqZJOQXE0_5CtAoDuyk6I0vX_wG2nv_RoTm8RPgSYN5_xqP6hWEPohFplMKr8dvkKKnJbG3iLuqZYsFK6TkEMuUjnJISB6XLFU3zWfAGripVG0zFNMwELiotY8UtCvvjo8sMSnQ&k=6LcmBQUTAAAAABRUqaI7Jt-bv9vr4Xpwh7MMVVW5&reason=i&type=image&lang=en&th=,hHVXdVSweSjAM18tQ1a2tP-YFW-TcMTwAAAB6aAAAASqawNj-xaxzfabbDAdRoS7PcfEJwaR7m5BEvu0Nm6eIst4ymEJkUcGyq8n4JwPptd-wjWVnlJEyA-tZPm8YzdhgLHjfhGUususM7Qh1SovD36nt8rpdzvSRiznoTNKdNiU1974mvG8hYI7mGXwavi73NW3idPuBf94M22eO_2o0atqdq7ERZoBbHxhe_qAI7FFGABePXUjoE4qy6q6bSwaNlSLQixu7jKxg7d2EAtuRcRLUeXashObldu_p2dYBBc9HFmVNQwAyL3TFwJP01PVbBIWpHNEJJ1T3tbrG9Ntk0Xsp7qSl8pVLEDgnFRBYpSOAGTQ9KxYSwSGXlNtL5XmbSkcOqWwuawMo2APiWog_vTM-qUdXqYq8OL1itjphEZzAh9YPp7GoTC3e01GTsOa36263ZmpOn5MAOJEDfEHAmipkDcMuTBtX86VnLNGLyrHxhptm5K5ybr9TGMsvrlnM8shMtVS25Imij0bkBhvgnoTIJMubBqb7PWFzBZ3_I5ZSotgaRemKesXPdzRwBlUJXovpcg7q1kRgDJNvnZXO65MMKeQm0lBWeSQz77Npvh_DszHhBvlag0GfZYv_SFmMJFj5KnosJx4q6C1dhnQTPvQbK3UWN85ArO31jwQKzlBTgOVw7mP7LeYRU0OiDyHiFsKKZXI0-h00oZ3qHWgqNb67qU29mvY-s6n3vk8_RPjTrxg_8JDL-Gl96m5CQVXm_zthVo3IicomUg6faxBB7m1w9hWrI2cgZLnWwbnCYED-oHTl86FEFJe5hkRu5coEwjpDolj4865MAOZd5XyAbeq6ctQyNnA13hl_z1HkRmek290AxBjr5VgZPLT8-V-F8bWquJB62NrB76aYS2uX52BB27ty4716_CInKVZQbxGX2jnefqlBE64nKpe72WIshawQ3ypKYVFWuiR26EH5YBUfIEM7nP0oTTrv4GDjjr-WkBt20rHq3u1IVqdsN8VGXvaYtG8-V8SO1UFqDqCXFzSBJJj9_UjHQrJ-AnPHCOvMv6zrHTI2bDczaK9LWNoMMUhHcqubDGCIODobgKp0UbrYI7z8nilBONUMGL2aaphTlY7ISIHuhCFgEHiEV1PuS0_XGqOnXB2bV_H7BCCKcPJOf4dVHqsXIbREUNus4obtiFNrkeK"], "isLeaf": false}, "http://www.google.com/recaptcha/api/reload?c=03AHJ_VusklXo3i4W1oVTV1_T7HfXCrtYSaTgY-TIJ2Rg-stiGU84z7wHlJKAE77gtTi443xpW20DKvHCFyo379t2SSSEsqZJOQXE0_5CtAoDuyk6I0vX_wG2nv_RoTm8RPgSYN5_xqP6hWEPohFplMKr8dvkKKnJbG3iLuqZYsFK6TkEMuUjnJISB6XLFU3zWfAGripVG0zFNMwELiotY8UtCvvjo8sMSnQ&k=6LcmBQUTAAAAABRUqaI7Jt-bv9vr4Xpwh7MMVVW5&reason=i&type=image&lang=en&th=,hHVXdVSweSjAM18tQ1a2tP-YFW-TcMTwAAAB6aAAAASqawNj-xaxzfabbDAdRoS7PcfEJwaR7m5BEvu0Nm6eIst4ymEJkUcGyq8n4JwPptd-wjWVnlJEyA-tZPm8YzdhgLHjfhGUususM7Qh1SovD36nt8rpdzvSRiznoTNKdNiU1974mvG8hYI7mGXwavi73NW3idPuBf94M22eO_2o0atqdq7ERZoBbHxhe_qAI7FFGABePXUjoE4qy6q6bSwaNlSLQixu7jKxg7d2EAtuRcRLUeXashObldu_p2dYBBc9HFmVNQwAyL3TFwJP01PVbBIWpHNEJJ1T3tbrG9Ntk0Xsp7qSl8pVLEDgnFRBYpSOAGTQ9KxYSwSGXlNtL5XmbSkcOqWwuawMo2APiWog_vTM-qUdXqYq8OL1itjphEZzAh9YPp7GoTC3e01GTsOa36263ZmpOn5MAOJEDfEHAmipkDcMuTBtX86VnLNGLyrHxhptm5K5ybr9TGMsvrlnM8shMtVS25Imij0bkBhvgnoTIJMubBqb7PWFzBZ3_I5ZSotgaRemKesXPdzRwBlUJXovpcg7q1kRgDJNvnZXO65MMKeQm0lBWeSQz77Npvh_DszHhBvlag0GfZYv_SFmMJFj5KnosJx4q6C1dhnQTPvQbK3UWN85ArO31jwQKzlBTgOVw7mP7LeYRU0OiDyHiFsKKZXI0-h00oZ3qHWgqNb67qU29mvY-s6n3vk8_RPjTrxg_8JDL-Gl96m5CQVXm_zthVo3IicomUg6faxBB7m1w9hWrI2cgZLnWwbnCYED-oHTl86FEFJe5hkRu5coEwjpDolj4865MAOZd5XyAbeq6ctQyNnA13hl_z1HkRmek290AxBjr5VgZPLT8-V-F8bWquJB62NrB76aYS2uX52BB27ty4716_CInKVZQbxGX2jnefqlBE64nKpe72WIshawQ3ypKYVFWuiR26EH5YBUfIEM7nP0oTTrv4GDjjr-WkBt20rHq3u1IVqdsN8VGXvaYtG8-V8SO1UFqDqCXFzSBJJj9_UjHQrJ-AnPHCOvMv6zrHTI2bDczaK9LWNoMMUhHcqubDGCIODobgKp0UbrYI7z8nilBONUMGL2aaphTlY7ISIHuhCFgEHiEV1PuS0_XGqOnXB2bV_H7BCCKcPJOf4dVHqsXIbREUNus4obtiFNrkeK": {"documentURL": "http://www.adf.ly/", "parent": "http://www.google.com/recaptcha/api/js/recaptcha.js?_=1496541612855", "url": "http://www.google.com/recaptcha/api/reload?c=03AHJ_VusklXo3i4W1oVTV1_T7HfXCrtYSaTgY-TIJ2Rg-stiGU84z7wHlJKAE77gtTi443xpW20DKvHCFyo379t2SSSEsqZJOQXE0_5CtAoDuyk6I0vX_wG2nv_RoTm8RPgSYN5_xqP6hWEPohFplMKr8dvkKKnJbG3iLuqZYsFK6TkEMuUjnJISB6XLFU3zWfAGripVG0zFNMwELiotY8UtCvvjo8sMSnQ&k=6LcmBQUTAAAAABRUqaI7Jt-bv9vr4Xpwh7MMVVW5&reason=i&type=image&lang=en&th=,hHVXdVSweSjAM18tQ1a2tP-YFW-TcMTwAAAB6aAAAASqawNj-xaxzfabbDAdRoS7PcfEJwaR7m5BEvu0Nm6eIst4ymEJkUcGyq8n4JwPptd-wjWVnlJEyA-tZPm8YzdhgLHjfhGUususM7Qh1SovD36nt8rpdzvSRiznoTNKdNiU1974mvG8hYI7mGXwavi73NW3idPuBf94M22eO_2o0atqdq7ERZoBbHxhe_qAI7FFGABePXUjoE4qy6q6bSwaNlSLQixu7jKxg7d2EAtuRcRLUeXashObldu_p2dYBBc9HFmVNQwAyL3TFwJP01PVbBIWpHNEJJ1T3tbrG9Ntk0Xsp7qSl8pVLEDgnFRBYpSOAGTQ9KxYSwSGXlNtL5XmbSkcOqWwuawMo2APiWog_vTM-qUdXqYq8OL1itjphEZzAh9YPp7GoTC3e01GTsOa36263ZmpOn5MAOJEDfEHAmipkDcMuTBtX86VnLNGLyrHxhptm5K5ybr9TGMsvrlnM8shMtVS25Imij0bkBhvgnoTIJMubBqb7PWFzBZ3_I5ZSotgaRemKesXPdzRwBlUJXovpcg7q1kRgDJNvnZXO65MMKeQm0lBWeSQz77Npvh_DszHhBvlag0GfZYv_SFmMJFj5KnosJx4q6C1dhnQTPvQbK3UWN85ArO31jwQKzlBTgOVw7mP7LeYRU0OiDyHiFsKKZXI0-h00oZ3qHWgqNb67qU29mvY-s6n3vk8_RPjTrxg_8JDL-Gl96m5CQVXm_zthVo3IicomUg6faxBB7m1w9hWrI2cgZLnWwbnCYED-oHTl86FEFJe5hkRu5coEwjpDolj4865MAOZd5XyAbeq6ctQyNnA13hl_z1HkRmek290AxBjr5VgZPLT8-V-F8bWquJB62NrB76aYS2uX52BB27ty4716_CInKVZQbxGX2jnefqlBE64nKpe72WIshawQ3ypKYVFWuiR26EH5YBUfIEM7nP0oTTrv4GDjjr-WkBt20rHq3u1IVqdsN8VGXvaYtG8-V8SO1UFqDqCXFzSBJJj9_UjHQrJ-AnPHCOvMv6zrHTI2bDczaK9LWNoMMUhHcqubDGCIODobgKp0UbrYI7z8nilBONUMGL2aaphTlY7ISIHuhCFgEHiEV1PuS0_XGqOnXB2bV_H7BCCKcPJOf4dVHqsXIbREUNus4obtiFNrkeK", "isRoot": false, "priority": "Low", "found_index": 85, "request_id": "5550.121", "type": "Script", "children": [], "isLeaf": true}, "http://cdn.adf.ly/static/image/button_join_now_tick.png": {"documentURL": "http://www.adf.ly/", "parent": "http://cdn.adf.ly/static/css/core46.css", "url": "http://cdn.adf.ly/static/image/button_join_now_tick.png", "isRoot": false, "priority": "Low", "found_index": 40, "request_id": "5550.62", "type": "Image", "children": [], "isLeaf": true}, "http://www.adf.ly/static/image/testimonials/monicacorrea_small.jpg": {"documentURL": "http://www.adf.ly/", "parent": "http://www.adf.ly/", "url": "http://www.adf.ly/static/image/testimonials/monicacorrea_small.jpg", "isRoot": false, "priority": "Low", "found_index": 20, "request_id": "5550.20", "type": "Image", "children": [], "isLeaf": true}, "http://cdn.adf.ly/static/js/index/index.js": {"documentURL": "http://www.adf.ly/", "parent": "http://www.adf.ly/", "url": "http://cdn.adf.ly/static/js/index/index.js", "isRoot": false, "priority": "Medium", "found_index": 21, "request_id": "5550.21", "type": "Script", "children": [], "isLeaf": true}, "http://cdn.adf.ly/static/image/scripts.png": {"documentURL": "http://www.adf.ly/", "parent": "http://cdn.adf.ly/static/css/core46.css", "url": "http://cdn.adf.ly/static/image/scripts.png", "isRoot": false, "priority": "Low", "found_index": 48, "request_id": "5550.70", "type": "Image", "children": [], "isLeaf": true}, "http://www.google.com/recaptcha/api/challenge?k=6LcmBQUTAAAAABRUqaI7Jt-bv9vr4Xpwh7MMVVW5&_=1496541612851": {"documentURL": "http://www.adf.ly/", "parent": "http://cdn.adf.ly/static/js/jquery-1.7.1.min.js", "url": "http://www.google.com/recaptcha/api/challenge?k=6LcmBQUTAAAAABRUqaI7Jt-bv9vr4Xpwh7MMVVW5&_=1496541612851", "isRoot": false, "priority": "Low", "found_index": 69, "request_id": "5550.99", "type": "Script", "children": [], "isLeaf": true}, "http://cdn.adf.ly/static/js/chosen.jquery.min.js": {"documentURL": "http://www.adf.ly/", "parent": "http://www.adf.ly/", "url": "http://cdn.adf.ly/static/js/chosen.jquery.min.js", "isRoot": false, "priority": "High", "found_index": 10, "request_id": "5550.10", "type": "Script", "children": [], "isLeaf": true}, "http://cdn.adf.ly/static/image/footer_bg.png": {"documentURL": "http://www.adf.ly/", "parent": "http://cdn.adf.ly/static/css/core46.css", "url": "http://cdn.adf.ly/static/image/footer_bg.png", "isRoot": false, "priority": "Low", "found_index": 54, "request_id": "5550.76", "type": "Image", "children": [], "isLeaf": true}, "http://cdn.adf.ly/static/js/home.js": {"documentURL": "http://www.adf.ly/", "parent": "http://www.adf.ly/", "url": "http://cdn.adf.ly/static/js/home.js", "isRoot": false, "priority": "High", "found_index": 17, "request_id": "5550.17", "type": "Script", "children": [], "isLeaf": true}, "http://cdn.adf.ly/static/css/jquery-ui/ui-lightness/jquery-ui-1.8.16.custom.css": {"documentURL": "http://www.adf.ly/", "parent": "http://www.adf.ly/", "url": "http://cdn.adf.ly/static/css/jquery-ui/ui-lightness/jquery-ui-1.8.16.custom.css", "isRoot": false, "priority": "VeryHigh", "found_index": 2, "request_id": "5550.2", "type": "Stylesheet", "children": [], "isLeaf": true}, "http://cdn.adf.ly/static/js/ie6-warning.js": {"documentURL": "http://www.adf.ly/", "parent": "http://www.adf.ly/", "url": "http://cdn.adf.ly/static/js/ie6-warning.js", "isRoot": false, "priority": "High", "found_index": 14, "request_id": "5550.14", "type": "Script", "children": [], "isLeaf": true}, "http://cdn.adf.ly/static/css/jquery-ui/ui-lightness/images/ui-bg_highlight-soft_100_eeeeee_1x100.png": {"documentURL": "http://www.adf.ly/", "parent": "http://cdn.adf.ly/static/js/jquery-1.7.1.min.js", "url": "http://cdn.adf.ly/static/css/jquery-ui/ui-lightness/images/ui-bg_highlight-soft_100_eeeeee_1x100.png", "isRoot": false, "priority": "Low", "found_index": 66, "request_id": "5550.96", "type": "Image", "children": [], "isLeaf": true}, "http://cdn.adf.ly/static/image/logo.png": {"documentURL": "http://www.adf.ly/", "parent": "http://cdn.adf.ly/static/css/core46.css", "url": "http://cdn.adf.ly/static/image/logo.png", "isRoot": false, "priority": "Low", "found_index": 34, "request_id": "5550.56", "type": "Image", "children": [], "isLeaf": true}, "https://static.xx.fbcdn.net/rsrc.php/v3/yD/r/FEppCFCt76d.png": {"documentURL": "https://www.facebook.com/v2.0/plugins/like.php?action=like&app_id=399141353502152&channel=http%3A%2F%2Fstaticxx.facebook.com%2Fconnect%2Fxd_arbiter%2Fr%2FD6ZfFsLEB4F.js%3Fversion%3D42%23cb%3Df2e1767fdd9b89%26domain%3Dwww.adf.ly%26origin%3Dhttp%253A%252F%252Fwww.adf.ly%252Ff9943e9dc72f28%26relation%3Dparent.parent&container_width=0&href=https%3A%2F%2Fwww.facebook.com%2FFB_SLUG&layout=standard&locale=en_US&sdk=joey&share=true&show_faces=true&width=280", "parent": "https://www.facebook.com/v2.0/plugins/like.php?action=like&app_id=399141353502152&channel=http%3A%2F%2Fstaticxx.facebook.com%2Fconnect%2Fxd_arbiter%2Fr%2FD6ZfFsLEB4F.js%3Fversion%3D42%23cb%3Df2e1767fdd9b89%26domain%3Dwww.adf.ly%26origin%3Dhttp%253A%252F%252Fwww.adf.ly%252Ff9943e9dc72f28%26relation%3Dparent.parent&container_width=0&href=https%3A%2F%2Fwww.facebook.com%2FFB_SLUG&layout=standard&locale=en_US&sdk=joey&share=true&show_faces=true&width=280", "url": "https://static.xx.fbcdn.net/rsrc.php/v3/yD/r/FEppCFCt76d.png", "isRoot": false, "priority": "VeryLow", "found_index": 82, "request_id": "5550.113", "type": "Image", "children": [], "isLeaf": true}, "http://cdn.adf.ly/static/image/quote_top_bg.png": {"documentURL": "http://www.adf.ly/", "parent": "http://cdn.adf.ly/static/css/core46.css", "url": "http://cdn.adf.ly/static/image/quote_top_bg.png", "isRoot": false, "priority": "Low", "found_index": 50, "request_id": "5550.72", "type": "Image", "children": [], "isLeaf": true}, "https://static.licdn.com/scds/concat/common/css?h=765zh9odycznutep5f0mj07m4-97r9i8f0vw2gmq97lpzb2ohek-7mxyksftlcjzimz2r05hd289r-4uu2pkz5u0jch61r2nhpyyrn8-aze4ooami6s3kk293iv0zfky1-7poavrvxlvh0irzkbnoyoginp-4om4nn3a2z730xs82d78xj3be-7m0xa9uspuliui8l4c806ppxc-ct4kfyj4tquup0bvqhttvymms-3pwwsn1udmwoy3iort8vfmygt-cfsam81o5sp3cxb7m0hs933c4-648sx8m8b6kj1srq42ztzy224-7yqnk453pnuqcyg5upg1cgpu2": {"documentURL": "https://www.linkedin.com/cws/followcompany?companyIdentifier=5359353&counterPosition=none&original_referer=http%3A%2F%2Fwww.adf.ly%2F&token=&isFramed=false&lang=en_US&_ts=1496541619861.3257&xd_origin_host=http%3A%2F%2Fwww.adf.ly", "parent": "https://www.linkedin.com/cws/followcompany?companyIdentifier=5359353&counterPosition=none&original_referer=http%3A%2F%2Fwww.adf.ly%2F&token=&isFramed=false&lang=en_US&_ts=1496541619861.3257&xd_origin_host=http%3A%2F%2Fwww.adf.ly", "url": "https://static.licdn.com/scds/concat/common/css?h=765zh9odycznutep5f0mj07m4-97r9i8f0vw2gmq97lpzb2ohek-7mxyksftlcjzimz2r05hd289r-4uu2pkz5u0jch61r2nhpyyrn8-aze4ooami6s3kk293iv0zfky1-7poavrvxlvh0irzkbnoyoginp-4om4nn3a2z730xs82d78xj3be-7m0xa9uspuliui8l4c806ppxc-ct4kfyj4tquup0bvqhttvymms-3pwwsn1udmwoy3iort8vfmygt-cfsam81o5sp3cxb7m0hs933c4-648sx8m8b6kj1srq42ztzy224-7yqnk453pnuqcyg5upg1cgpu2", "isRoot": false, "priority": "VeryLow", "found_index": 88, "request_id": "5550.124", "type": "Stylesheet", "children": [], "isLeaf": true}, "http://cdn.adf.ly/static/image/ft_payoneer.png": {"documentURL": "http://www.adf.ly/", "parent": "http://cdn.adf.ly/static/css/core46.css", "url": "http://cdn.adf.ly/static/image/ft_payoneer.png", "isRoot": false, "priority": "Low", "found_index": 58, "request_id": "5550.82", "type": "Image", "children": [], "isLeaf": true}, "http://cdn.adf.ly/static/image/language_arrows.png": {"documentURL": "http://www.adf.ly/", "parent": "http://cdn.adf.ly/static/css/core46.css", "url": "http://cdn.adf.ly/static/image/language_arrows.png", "isRoot": false, "priority": "Low", "found_index": 33, "request_id": "5550.55", "type": "Image", "children": [], "isLeaf": true}, "https://static.xx.fbcdn.net/rsrc.php/v3iSgH4/yb/l/en_US/RcW9ItWDVXf.js": {"documentURL": "https://www.facebook.com/v2.0/plugins/like.php?action=like&app_id=399141353502152&channel=http%3A%2F%2Fstaticxx.facebook.com%2Fconnect%2Fxd_arbiter%2Fr%2FD6ZfFsLEB4F.js%3Fversion%3D42%23cb%3Df2e1767fdd9b89%26domain%3Dwww.adf.ly%26origin%3Dhttp%253A%252F%252Fwww.adf.ly%252Ff9943e9dc72f28%26relation%3Dparent.parent&container_width=0&href=https%3A%2F%2Fwww.facebook.com%2FFB_SLUG&layout=standard&locale=en_US&sdk=joey&share=true&show_faces=true&width=280", "parent": "https://www.facebook.com/v2.0/plugins/like.php?action=like&app_id=399141353502152&channel=http%3A%2F%2Fstaticxx.facebook.com%2Fconnect%2Fxd_arbiter%2Fr%2FD6ZfFsLEB4F.js%3Fversion%3D42%23cb%3Df2e1767fdd9b89%26domain%3Dwww.adf.ly%26origin%3Dhttp%253A%252F%252Fwww.adf.ly%252Ff9943e9dc72f28%26relation%3Dparent.parent&container_width=0&href=https%3A%2F%2Fwww.facebook.com%2FFB_SLUG&layout=standard&locale=en_US&sdk=joey&share=true&show_faces=true&width=280", "url": "https://static.xx.fbcdn.net/rsrc.php/v3iSgH4/yb/l/en_US/RcW9ItWDVXf.js", "isRoot": false, "priority": "VeryLow", "found_index": 83, "request_id": "5550.114", "type": "Script", "children": [], "isLeaf": true}, "http://cdn.adf.ly/static/image/arrow.png": {"documentURL": "http://www.adf.ly/", "parent": "http://cdn.adf.ly/static/css/core46.css", "url": "http://cdn.adf.ly/static/image/arrow.png", "isRoot": false, "priority": "Low", "found_index": 42, "request_id": "5550.64", "type": "Image", "children": [], "isLeaf": true}, "http://cdn.adf.ly/static/image/footer_home_lr_bg.png": {"documentURL": "http://www.adf.ly/", "parent": "http://cdn.adf.ly/static/css/core46.css", "url": "http://cdn.adf.ly/static/image/footer_home_lr_bg.png", "isRoot": false, "priority": "Low", "found_index": 55, "request_id": "5550.77", "type": "Image", "children": [], "isLeaf": true}, "http://cdn.adf.ly/static/image/safe.png": {"documentURL": "http://www.adf.ly/", "parent": "http://cdn.adf.ly/static/css/core46.css", "url": "http://cdn.adf.ly/static/image/safe.png", "isRoot": false, "priority": "Low", "found_index": 43, "request_id": "5550.65", "type": "Image", "children": [], "isLeaf": true}, "http://m.addthis.com/live/red_lojson/300lo.json?si=593369ab2efd622a&bkl=0&bl=1&pdt=361&sid=593369ab2efd622a&pub=ra-53993a6f0d2e8c74&rev=v7.9.5-wp&ln=en&pc=men&cb=0&ab=-&dp=www.adf.ly&fp=&fr=&of=0&pd=0&irt=1&vcl=1&md=0&ct=1&tct=0&abt=0&cdn=0&pi=1&rb=0&gen=100&chr=UTF-8&mk=adfly%2Cadf.ly%2Cshort%20links%2Ctinyurl%2Cbitly%2Cbit.ly%2Cearn%20money%2Clink%20advertising%2Ctiny%20url%2Curl%20shortener&colc=1496541612989&jsl=161&uvs=5933697a9703ad54002&skipb=1&callback=addthis.cbs.oln9_118435636894462790": {"documentURL": "http://www.adf.ly/", "parent": "http://s7.addthis.com/js/300/addthis_widget.js", "url": "http://m.addthis.com/live/red_lojson/300lo.json?si=593369ab2efd622a&bkl=0&bl=1&pdt=361&sid=593369ab2efd622a&pub=ra-53993a6f0d2e8c74&rev=v7.9.5-wp&ln=en&pc=men&cb=0&ab=-&dp=www.adf.ly&fp=&fr=&of=0&pd=0&irt=1&vcl=1&md=0&ct=1&tct=0&abt=0&cdn=0&pi=1&rb=0&gen=100&chr=UTF-8&mk=adfly%2Cadf.ly%2Cshort%20links%2Ctinyurl%2Cbitly%2Cbit.ly%2Cearn%20money%2Clink%20advertising%2Ctiny%20url%2Curl%20shortener&colc=1496541612989&jsl=161&uvs=5933697a9703ad54002&skipb=1&callback=addthis.cbs.oln9_118435636894462790", "isRoot": false, "priority": "Low", "found_index": 72, "request_id": "5550.102", "type": "Script", "children": [], "isLeaf": true}, "http://cdn.adf.ly/static/js/jquery.placeholder.min.js": {"documentURL": "http://www.adf.ly/", "parent": "http://www.adf.ly/", "url": "http://cdn.adf.ly/static/js/jquery.placeholder.min.js", "isRoot": false, "priority": "High", "found_index": 8, "request_id": "5550.8", "type": "Script", "children": [], "isLeaf": true}, "https://platform.linkedin.com/js/secureAnonymousFramework?v=0.0.2000-RC8.59768-1429&lang=en_US": {"isRoot": false, "parent": "http://platform.linkedin.com/in.js", "url": "https://platform.linkedin.com/js/secureAnonymousFramework?v=0.0.2000-RC8.59768-1429&lang=en_US", "priority": "Low", "found_index": 28, "request_id": "5550.50", "type": "Script", "children": ["https://platform.linkedin.com/js/xdrpc.html?v=0.0.2000-RC8.59768-1429"], "isLeaf": false, "documentURL": "http://www.adf.ly/"}, "http://cdn.adf.ly/static/image/paid_bg.png": {"documentURL": "http://www.adf.ly/", "parent": "http://cdn.adf.ly/static/css/core46.css", "url": "http://cdn.adf.ly/static/image/paid_bg.png", "isRoot": false, "priority": "Low", "found_index": 38, "request_id": "5550.60", "type": "Image", "children": [], "isLeaf": true}, "http://cdn.adf.ly/static/css/core46.css": {"isRoot": false, "parent": "http://www.adf.ly/", "url": "http://cdn.adf.ly/static/css/core46.css", "priority": "VeryHigh", "found_index": 4, "request_id": "5550.4", "type": "Stylesheet", "children": ["http://cdn.adf.ly/static/image/footer_home_lr_bg.png", "http://cdn.adf.ly/static/image/footer_bg.png", "http://cdn.adf.ly/static/image/num_bg.png", "http://cdn.adf.ly/static/image/links_clicked_bg.png", "http://cdn.adf.ly/static/image/blockquote_bg.png", "http://cdn.adf.ly/static/image/quote_top_bg.png", "http://cdn.adf.ly/static/image/quote_photo_bg.png", "http://cdn.adf.ly/static/image/scripts.png", "http://cdn.adf.ly/static/image/footer_home_ll_bg.png", "http://cdn.adf.ly/static/image/ft_alertpay.png", "http://cdn.adf.ly/static/image/arrow.png", "http://cdn.adf.ly/static/image/safe.png", "http://cdn.adf.ly/static/image/ads.png", "http://cdn.adf.ly/static/image/lmp.png", "http://cdn.adf.ly/static/image/paid_bg.png", "http://cdn.adf.ly/static/image/share_bg.png", "http://cdn.adf.ly/static/image/button_join_now_tick.png", "http://cdn.adf.ly/static/image/fb_f.png", "http://cdn.adf.ly/static/image/stats.png", "http://cdn.adf.ly/static/image/api.png", "http://cdn.adf.ly/static/image/header_gradient.jpg", "http://cdn.adf.ly/static/image/header.png", "http://cdn.adf.ly/static/image/header_bg.png", "http://cdn.adf.ly/static/image/language_arrows.png", "http://cdn.adf.ly/static/image/language_flags.png", "http://cdn.adf.ly/static/image/shrink_bg.png", "http://cdn.adf.ly/static/image/logo.png", "http://cdn.adf.ly/static/image/register_bg.png", "http://cdn.adf.ly/static/image/shrink_button_icon.png", "http://cdn.adf.ly/static/image/ft_payoneer.png", "http://cdn.adf.ly/static/image/ft_paypal.png"], "isLeaf": false, "documentURL": "http://www.adf.ly/"}, "http://www.google.com/recaptcha/api/image?c=03AHJ_VusklXo3i4W1oVTV1_T7HfXCrtYSaTgY-TIJ2Rg-stiGU84z7wHlJKAE77gtTi443xpW20DKvHCFyo379t2SSSEsqZJOQXE0_5CtAoDuyk6I0vX_wG2nv_RoTm8RPgSYN5_xqP6hWEPohFplMKr8dvkKKnJbG3iLuqZYsFK6TkEMuUjnJISB6XLFU3zWfAGripVG0zFNMwELiotY8UtCvvjo8sMSnQ&th=,YpNXk7KweSjAM18tQ1a2tP-YFW-TcMTwAAAB6aAAAAOXawNj-xaxzfabbDAdRoS7PcfEJwaR7m5BEvu0Nm6eIst4ymEJkUcGyq8n4JwPptd-wjWVnlJEyA-tZPm8YzdhgLHjfhGUususM7Qh1SovD36nt8rpdzvSRiznoTNKdNiU1974mvG8hYI7mGXwavi73NW3idPuBf94M22eO_2o0atqdq7ERZoBbHxhe_qAI7FFGABePXUjoE4qy6q6bSwaNlSLQixu7jKxg7d2EAtuRcRLUeXashObize_p2dYBBdRVLUgnnCZdPX5R1d9xcZE0y8dPkHOIEIjj4WltmgpUQarPBkTYsjAojJvOLwPgswQlGA7iXQFHPHW6oMrFtYPK1wSyr_Pv0vKgz_lVbfjtLdc5_lmFGdygwRrcOlYBYvHu0Tft-SoPZGrSA1VoKlkIBXxWn_KQ_0Da7Jb9BKyva_ykSzacdAfYqRhoUL3Eu9HjL2t-hoJkBpFoPIvHIxK7PwokD3iTihB71ERge8Z5RynAQbFzR-C1AZW9gdj_mowuX2cwgqy26tc6TOWh-FlwnZNq-m9tZnAkI6AZlIjUjkp_zqIXCbpwQIbS5oefEeeybBonk3tMCTNbahFF_ZjIHdZyohnBWAJQQiu1QcUdHqdvPP9yvm9IExYQogfpHHkepsn_PVsYCRnBKT-RtjJ4_xh0msJSkBj3mwI-whGa1TfTUjFMQNjnRv6SzewPzGG_wBCOUAZVSJrh-G69IqXWLT3rEoORqBhJecGV9_44chPSPciKynGhC01dmQgnBbjNQXfu_N_l4zlqU1FKeq0EHvX6q-fLak3SWZbens-S0f4KCl2iTeIJhBWcCSOvJ5mQX2H_Ry9CDDZuSRFBRWu_GHacl_AFrQB6OfioyZzmSBU2t9-b0kJTD_UDAJhrepm5LhQxVZFdZd1wUsZPKIFyR38Ql-AWrJoFEAyVlxvSho38nIfbkNG-wa1Q7Q8_I1HSsGxXtCYZ98FevijGB5Otpn5wnFYRwgPyggRrIGd0-0w2OwgLzdaJu0-Z_-bixRpcycMeTZKqje9Jryd76-69te8gjWal-rDsbB6vwnt2TsqBKt-N05XONA94N-NXg1KwDlLZEC-d4Fi66uhpkKo7icBxAi8H8koi35BJP2TFODH0ESOeRYDYFLF9FmNJui_tODibK8K": {"documentURL": "http://www.adf.ly/", "parent": "http://www.adf.ly/", "url": "http://www.google.com/recaptcha/api/image?c=03AHJ_VusklXo3i4W1oVTV1_T7HfXCrtYSaTgY-TIJ2Rg-stiGU84z7wHlJKAE77gtTi443xpW20DKvHCFyo379t2SSSEsqZJOQXE0_5CtAoDuyk6I0vX_wG2nv_RoTm8RPgSYN5_xqP6hWEPohFplMKr8dvkKKnJbG3iLuqZYsFK6TkEMuUjnJISB6XLFU3zWfAGripVG0zFNMwELiotY8UtCvvjo8sMSnQ&th=,YpNXk7KweSjAM18tQ1a2tP-YFW-TcMTwAAAB6aAAAAOXawNj-xaxzfabbDAdRoS7PcfEJwaR7m5BEvu0Nm6eIst4ymEJkUcGyq8n4JwPptd-wjWVnlJEyA-tZPm8YzdhgLHjfhGUususM7Qh1SovD36nt8rpdzvSRiznoTNKdNiU1974mvG8hYI7mGXwavi73NW3idPuBf94M22eO_2o0atqdq7ERZoBbHxhe_qAI7FFGABePXUjoE4qy6q6bSwaNlSLQixu7jKxg7d2EAtuRcRLUeXashObize_p2dYBBdRVLUgnnCZdPX5R1d9xcZE0y8dPkHOIEIjj4WltmgpUQarPBkTYsjAojJvOLwPgswQlGA7iXQFHPHW6oMrFtYPK1wSyr_Pv0vKgz_lVbfjtLdc5_lmFGdygwRrcOlYBYvHu0Tft-SoPZGrSA1VoKlkIBXxWn_KQ_0Da7Jb9BKyva_ykSzacdAfYqRhoUL3Eu9HjL2t-hoJkBpFoPIvHIxK7PwokD3iTihB71ERge8Z5RynAQbFzR-C1AZW9gdj_mowuX2cwgqy26tc6TOWh-FlwnZNq-m9tZnAkI6AZlIjUjkp_zqIXCbpwQIbS5oefEeeybBonk3tMCTNbahFF_ZjIHdZyohnBWAJQQiu1QcUdHqdvPP9yvm9IExYQogfpHHkepsn_PVsYCRnBKT-RtjJ4_xh0msJSkBj3mwI-whGa1TfTUjFMQNjnRv6SzewPzGG_wBCOUAZVSJrh-G69IqXWLT3rEoORqBhJecGV9_44chPSPciKynGhC01dmQgnBbjNQXfu_N_l4zlqU1FKeq0EHvX6q-fLak3SWZbens-S0f4KCl2iTeIJhBWcCSOvJ5mQX2H_Ry9CDDZuSRFBRWu_GHacl_AFrQB6OfioyZzmSBU2t9-b0kJTD_UDAJhrepm5LhQxVZFdZd1wUsZPKIFyR38Ql-AWrJoFEAyVlxvSho38nIfbkNG-wa1Q7Q8_I1HSsGxXtCYZ98FevijGB5Otpn5wnFYRwgPyggRrIGd0-0w2OwgLzdaJu0-Z_-bixRpcycMeTZKqje9Jryd76-69te8gjWal-rDsbB6vwnt2TsqBKt-N05XONA94N-NXg1KwDlLZEC-d4Fi66uhpkKo7icBxAi8H8koi35BJP2TFODH0ESOeRYDYFLF9FmNJui_tODibK8K", "isRoot": false, "priority": "Low", "found_index": 86, "request_id": "5550.122", "type": "Image", "children": [], "isLeaf": true}, "http://cdn.adf.ly/static/image/share_bg.png": {"documentURL": "http://www.adf.ly/", "parent": "http://cdn.adf.ly/static/css/core46.css", "url": "http://cdn.adf.ly/static/image/share_bg.png", "isRoot": false, "priority": "Low", "found_index": 39, "request_id": "5550.61", "type": "Image", "children": [], "isLeaf": true}, "http://cdn.adf.ly/static/css/jquery.loadmask.css": {"documentURL": "http://www.adf.ly/", "parent": "http://www.adf.ly/", "url": "http://cdn.adf.ly/static/css/jquery.loadmask.css", "isRoot": false, "priority": "VeryHigh", "found_index": 3, "request_id": "5550.3", "type": "Stylesheet", "children": [], "isLeaf": true}, "https://www.linkedin.com/cws/followcompany?companyIdentifier=5359353&counterPosition=none&original_referer=http%3A%2F%2Fwww.adf.ly%2F&token=&isFramed=false&lang=en_US&_ts=1496541619861.3257&xd_origin_host=http%3A%2F%2Fwww.adf.ly": {"isRoot": false, "parent": "https://platform.linkedin.com/js/xdrpc.html?v=0.0.2000-RC8.59768-1429", "url": "https://www.linkedin.com/cws/followcompany?companyIdentifier=5359353&counterPosition=none&original_referer=http%3A%2F%2Fwww.adf.ly%2F&token=&isFramed=false&lang=en_US&_ts=1496541619861.3257&xd_origin_host=http%3A%2F%2Fwww.adf.ly", "priority": "VeryLow", "found_index": 87, "request_id": "5550.123", "type": "Document", "children": ["https://static.licdn.com/scds/concat/common/js?h=b04y4p1rkdv631n988yzucz8q", "https://static.licdn.com/scds/concat/common/css?h=765zh9odycznutep5f0mj07m4-97r9i8f0vw2gmq97lpzb2ohek-7mxyksftlcjzimz2r05hd289r-4uu2pkz5u0jch61r2nhpyyrn8-aze4ooami6s3kk293iv0zfky1-7poavrvxlvh0irzkbnoyoginp-4om4nn3a2z730xs82d78xj3be-7m0xa9uspuliui8l4c806ppxc-ct4kfyj4tquup0bvqhttvymms-3pwwsn1udmwoy3iort8vfmygt-cfsam81o5sp3cxb7m0hs933c4-648sx8m8b6kj1srq42ztzy224-7yqnk453pnuqcyg5upg1cgpu2", "https://www.linkedin.com/uas/js/anonymoususerspace", "https://static.licdn.com/scds/concat/common/js?h=a0jta68t22m53ctufp62mjb9b-3l5b0m8v4ywigyorwrawyorqp-1qxt69eezmfo5p7guan5m28k2-9ahtd75n2fngapkt47zxa83l4-6yo19j3zbvfkaftihaqj2wc8w-e34cdkc3cj077ikcayyyu2wpj-djvfw8en5rvj07kmioaklpk4z-el185lpi61t6smwdvp596sh6y-4ofin259c3rzrgxsz7haoevdt-1yevi40jf10exl64ba3pbm14t-84wiass0xmq0bsclerixvl4m0-cub2uboipu4ax82cvyddnnoea-1n8sluvsemdb4gb3xm7zgz652-8h350yj4rwtwp973benlp6pil-2v6nrp0wa0nlrkpmb32i62enx-9yapbb9c5ce3w0tjhqp8s1ben-be35lq69dqsbgl8h9t4bqpy08-avftajdh5oq2u6k2vaor3czdy-2r5gveucqe4lsolc3n0oljsn1-e9rsfv7b5gx0bk0tln31dx3sq-c8ha6zrgpgcni7poa5ctye7il-51dv6schthjydhvcv6rxvospp-b88qxy99s08xoes3weacd08uc-4805qyau5m6n9u7wprikb8gtg-bwrd332dvhbcfx9p9k3ge4w1v-5gedbbq7rksg5ypd5ruwisrah-diqd38xo23p6u922ihupn59iv-2swpl0141fhjbvotjp0vhbq5p", "https://static.licdn.com/scds/concat/common/css?h=8lpissn6x7y2031ehsfug0tan"], "isLeaf": false, "documentURL": "https://www.linkedin.com/cws/followcompany?companyIdentifier=5359353&counterPosition=none&original_referer=http%3A%2F%2Fwww.adf.ly%2F&token=&isFramed=false&lang=en_US&_ts=1496541619861.3257&xd_origin_host=http%3A%2F%2Fwww.adf.ly"}, "http://www.google.com/recaptcha/api/reload?c=03AHJ_VusivURfPEBJ4k-MHVHZx3hUJPm5uwdZZ-6mOeT-lsnz6gnhZ8jP3nODtrXBgSC8tS1tIyKmcvEDroa5NgzQ7e1cvdz0-CWySJqT4d08XKgfY36flE-sccmBJTEqUDDtu9qkGWpD-KE3w2NRPKLIaozTEEKYxkOyoxN0PfwcWsM4KhMVf8UaielSgBfznwY7zRKftsSD&k=6LcmBQUTAAAAABRUqaI7Jt-bv9vr4Xpwh7MMVVW5&reason=i&type=image&lang=en&th=,BPVX9dSweSjAM18tQ1a2tP-YFW-TcMTwAAABZKAAAARyawNjCVwC85U2ioewatMCFlJCSthtevX9udZvGKL3ULaVaWzpE3QvvGDnYUhj_lQHyPCpQrOJ-zvN225EDt5puPe_nGrt5BOFj_9FyUgQb9yeNlR0jXY9PPJ-0-Go3rFJBKId2GRKgGTddZ_kOUVD7evBMpls1mwv-PCKjmtfvfZrJRrh6RNuUpA6xHcFhvDpXkJKgXHiNoaVcpPDVTa3cD1P1BM2Hp8xl7uKQtTBGT6guNrAn3ML6llXDyeSpZwI9QpbLUXoJHV8uZy3F7xUeGikNgiKWnFm-cig_wSdCvrBO55AoRfsI3i5afXyTLr7DG79xXtAlxhImV6U1WMDVj_VIOAozunWMxYjVoebAXApNIQd_uJvIdDN678WUqdb7RfJhnvA5z2l56jsvvWFbpPmE41jSfiwHT3qGrbs3eLj-hhgYHUMFI4jzMyHr3cb4_yPG-28uNSVSxhz79ZoWjj-GBbbKpjTnsGZjeQtdCgFfze-zTnDJ4GbcjkicQ-rUjbj2BWSd86q0LuNjMGZV8f9A6yO6arLTcfh_rJTYY2BunDusGuD9BiN05dUwqBFssOErh1BpOXUrM8Dv__IqvCBxQ-FsQEuFTjVmJ3F_CHZjFgRV3Qs8uPqC0CrboM97a-A2s4RHAM1kwMchxSujiwWtK0Kq1_lrbFOv8-2f-xcZGcb41dN1JDpE3l7sIiP0IWoG8XhgaE676B6JFUrrzOMlSWXjqycZvyA5eATClOCm54T7-2dt63fpSYCEAl3GSmKBc_iOhlx7Eha94LvuNeGH5dTJ246_cZMIadpT8I_kD9wvGkEnom_pKGRZqOircHCcN21eioJ31xyZ8ouzyrxGzchP3o0rJ3hGz5PWHr_GsZKtwv_BuSHerrVOlTXTrSbialTs0yID-sxAcPBGuR9eUWEtRDiS2BTw714So11tJsIQdP5Xs10z0lGub822QVZIkx-kQ8MHEMonyc3DPs1sHpl22VTZC-5or2azhLsgAyp2bJxzEAQVWFkyhsBOLfc8XC5VtshPKZfvxLXo6I7r7CSkDdpfjQZQVA8MGTU3F_has7Ft3DKUwvssLFHpLJ-06apaYBE2lcHnM_7okBCrWBVqIskQsh-wcUeJZZIlQTSIzYCZyu7U5HBUN-DpzJhHsER": {"documentURL": "http://www.adf.ly/", "parent": "http://www.google.com/recaptcha/api/js/recaptcha.js", "url": "http://www.google.com/recaptcha/api/reload?c=03AHJ_VusivURfPEBJ4k-MHVHZx3hUJPm5uwdZZ-6mOeT-lsnz6gnhZ8jP3nODtrXBgSC8tS1tIyKmcvEDroa5NgzQ7e1cvdz0-CWySJqT4d08XKgfY36flE-sccmBJTEqUDDtu9qkGWpD-KE3w2NRPKLIaozTEEKYxkOyoxN0PfwcWsM4KhMVf8UaielSgBfznwY7zRKftsSD&k=6LcmBQUTAAAAABRUqaI7Jt-bv9vr4Xpwh7MMVVW5&reason=i&type=image&lang=en&th=,BPVX9dSweSjAM18tQ1a2tP-YFW-TcMTwAAABZKAAAARyawNjCVwC85U2ioewatMCFlJCSthtevX9udZvGKL3ULaVaWzpE3QvvGDnYUhj_lQHyPCpQrOJ-zvN225EDt5puPe_nGrt5BOFj_9FyUgQb9yeNlR0jXY9PPJ-0-Go3rFJBKId2GRKgGTddZ_kOUVD7evBMpls1mwv-PCKjmtfvfZrJRrh6RNuUpA6xHcFhvDpXkJKgXHiNoaVcpPDVTa3cD1P1BM2Hp8xl7uKQtTBGT6guNrAn3ML6llXDyeSpZwI9QpbLUXoJHV8uZy3F7xUeGikNgiKWnFm-cig_wSdCvrBO55AoRfsI3i5afXyTLr7DG79xXtAlxhImV6U1WMDVj_VIOAozunWMxYjVoebAXApNIQd_uJvIdDN678WUqdb7RfJhnvA5z2l56jsvvWFbpPmE41jSfiwHT3qGrbs3eLj-hhgYHUMFI4jzMyHr3cb4_yPG-28uNSVSxhz79ZoWjj-GBbbKpjTnsGZjeQtdCgFfze-zTnDJ4GbcjkicQ-rUjbj2BWSd86q0LuNjMGZV8f9A6yO6arLTcfh_rJTYY2BunDusGuD9BiN05dUwqBFssOErh1BpOXUrM8Dv__IqvCBxQ-FsQEuFTjVmJ3F_CHZjFgRV3Qs8uPqC0CrboM97a-A2s4RHAM1kwMchxSujiwWtK0Kq1_lrbFOv8-2f-xcZGcb41dN1JDpE3l7sIiP0IWoG8XhgaE676B6JFUrrzOMlSWXjqycZvyA5eATClOCm54T7-2dt63fpSYCEAl3GSmKBc_iOhlx7Eha94LvuNeGH5dTJ246_cZMIadpT8I_kD9wvGkEnom_pKGRZqOircHCcN21eioJ31xyZ8ouzyrxGzchP3o0rJ3hGz5PWHr_GsZKtwv_BuSHerrVOlTXTrSbialTs0yID-sxAcPBGuR9eUWEtRDiS2BTw714So11tJsIQdP5Xs10z0lGub822QVZIkx-kQ8MHEMonyc3DPs1sHpl22VTZC-5or2azhLsgAyp2bJxzEAQVWFkyhsBOLfc8XC5VtshPKZfvxLXo6I7r7CSkDdpfjQZQVA8MGTU3F_has7Ft3DKUwvssLFHpLJ-06apaYBE2lcHnM_7okBCrWBVqIskQsh-wcUeJZZIlQTSIzYCZyu7U5HBUN-DpzJhHsER", "isRoot": false, "priority": "Low", "found_index": 81, "request_id": "5550.111", "type": "Script", "children": [], "isLeaf": true}, "http://www.google.com/recaptcha/api/challenge?k=6LcmBQUTAAAAABRUqaI7Jt-bv9vr4Xpwh7MMVVW5": {"isRoot": false, "parent": "http://www.adf.ly/", "url": "http://www.google.com/recaptcha/api/challenge?k=6LcmBQUTAAAAABRUqaI7Jt-bv9vr4Xpwh7MMVVW5", "priority": "Medium", "found_index": 24, "request_id": "5550.24", "type": "Script", "children": ["http://www.google.com/recaptcha/api/js/recaptcha.js"], "isLeaf": false, "documentURL": "http://www.adf.ly/"}, "http://cdn.adf.ly/static/image/header_bg.png": {"documentURL": "http://www.adf.ly/", "parent": "http://cdn.adf.ly/static/css/core46.css", "url": "http://cdn.adf.ly/static/image/header_bg.png", "isRoot": false, "priority": "Low", "found_index": 30, "request_id": "5550.52", "type": "Image", "children": [], "isLeaf": true}, "http://cdn.adf.ly/static/image/lmp.png": {"documentURL": "http://www.adf.ly/", "parent": "http://cdn.adf.ly/static/css/core46.css", "url": "http://cdn.adf.ly/static/image/lmp.png", "isRoot": false, "priority": "Low", "found_index": 45, "request_id": "5550.67", "type": "Image", "children": [], "isLeaf": true}, "http://cdn.adf.ly/static/js/jquery.loadmask.min.js": {"documentURL": "http://www.adf.ly/", "parent": "http://www.adf.ly/", "url": "http://cdn.adf.ly/static/js/jquery.loadmask.min.js", "isRoot": false, "priority": "High", "found_index": 9, "request_id": "5550.9", "type": "Script", "children": [], "isLeaf": true}, "https://static.licdn.com/scds/common/u/images/apps/connect/sprites/sprite_connect_v15.png": {"documentURL": "https://www.linkedin.com/cws/followcompany?companyIdentifier=5359353&counterPosition=none&original_referer=http%3A%2F%2Fwww.adf.ly%2F&token=&isFramed=false&lang=en_US&_ts=1496541619861.3257&xd_origin_host=http%3A%2F%2Fwww.adf.ly", "parent": "https://static.licdn.com/scds/concat/common/js?h=a0jta68t22m53ctufp62mjb9b-3l5b0m8v4ywigyorwrawyorqp-1qxt69eezmfo5p7guan5m28k2-9ahtd75n2fngapkt47zxa83l4-6yo19j3zbvfkaftihaqj2wc8w-e34cdkc3cj077ikcayyyu2wpj-djvfw8en5rvj07kmioaklpk4z-el185lpi61t6smwdvp596sh6y-4ofin259c3rzrgxsz7haoevdt-1yevi40jf10exl64ba3pbm14t-84wiass0xmq0bsclerixvl4m0-cub2uboipu4ax82cvyddnnoea-1n8sluvsemdb4gb3xm7zgz652-8h350yj4rwtwp973benlp6pil-2v6nrp0wa0nlrkpmb32i62enx-9yapbb9c5ce3w0tjhqp8s1ben-be35lq69dqsbgl8h9t4bqpy08-avftajdh5oq2u6k2vaor3czdy-2r5gveucqe4lsolc3n0oljsn1-e9rsfv7b5gx0bk0tln31dx3sq-c8ha6zrgpgcni7poa5ctye7il-51dv6schthjydhvcv6rxvospp-b88qxy99s08xoes3weacd08uc-4805qyau5m6n9u7wprikb8gtg-bwrd332dvhbcfx9p9k3ge4w1v-5gedbbq7rksg5ypd5ruwisrah-diqd38xo23p6u922ihupn59iv-2swpl0141fhjbvotjp0vhbq5p", "url": "https://static.licdn.com/scds/common/u/images/apps/connect/sprites/sprite_connect_v15.png", "isRoot": false, "priority": "VeryLow", "found_index": 93, "request_id": "5550.138", "type": "Image", "children": [], "isLeaf": true}, "http://www.google.com/recaptcha/api/img/red/help.gif": {"documentURL": "http://www.adf.ly/", "parent": "http://www.adf.ly/", "url": "http://www.google.com/recaptcha/api/img/red/help.gif", "isRoot": false, "priority": "Low", "found_index": 78, "request_id": "5550.108", "type": "Image", "children": [], "isLeaf": true}, "http://cdn.adf.ly/static/image/fb_f.png": {"documentURL": "http://www.adf.ly/", "parent": "http://cdn.adf.ly/static/css/core46.css", "url": "http://cdn.adf.ly/static/image/fb_f.png", "isRoot": false, "priority": "Low", "found_index": 41, "request_id": "5550.63", "type": "Image", "children": [], "isLeaf": true}, "http://www.google.com/recaptcha/api/img/red/text.gif": {"documentURL": "http://www.adf.ly/", "parent": "http://www.adf.ly/", "url": "http://www.google.com/recaptcha/api/img/red/text.gif", "isRoot": false, "priority": "Low", "found_index": 77, "request_id": "5550.107", "type": "Image", "children": [], "isLeaf": true}, "http://www.google.com/recaptcha/api/image?c=03AHJ_VusklXo3i4W1oVTV1_T7HfXCrtYSaTgY-TIJ2Rg-stiGU84z7wHlJKAE77gtTi443xpW20DKvHCFyo379t2SSSEsqZJOQXE0_5CtAoDuyk6I0vX_wG2nv_RoTm8RPgSYN5_xqP6hWEPohFplMKr8dvkKKnJbG3iLuqZYsFK6TkEMuUjnJISB6XLFU3zWfAGripVG0zFNMwELiotY8UtCvvjo8sMSnQ&th=,BfRX9NWweSjAM18tQ1a2tP-YFW-TcMTwAAAB6aAAAAS3awNj-xaxzfabbDAdRoS7PcfEJwaR7m5BEvu0Nm6eIst4ymEJkUcGyq8n4JwPptd-wjWVnlJEyA-tZPm8YzdhgLHjfhGUususM7Qh1SovD36nt8rpdzvSRiznoTNKdNiU1974mvG8hYI7mGXwavi73NW3idPuBf94M22eO_2o0atqdq7ERZoBbHxhe_qAI7FFGABePXUjoE4qy6q6bSwaNlSLQixu7jKxg7d2EAtuRcRLUeXashObkK-_p2dYBBfzTf_h_4-q2P7maqTzSamPVJEZcWfK81o7qBpgS74qeRPhM0CvulRatUHSpz4PBXG1y9LfvDw8g2bzKDMbSIzDT0GxJ6vYku8ldwd3RGCR9zQrLmsNBoUDcNB3Bfd6z4TZb0C_rYhT2wst1W70deoR7Fnwg3zKPT_91fuDT7HKW4JUjpSUotr0Bl0QWS8ihESyb05DlgXzFZRz_ZXdwB1IqRVG_tclx6J5JvylXftnTtIv8GMhTrjtZoEmRAwlgpu3IZxu7u01S5pLQoJGhxVuHahrIP17oHeTCt11UES3Z0H3kEHs5eS1mn6UeLs6ZSI9MeeHFyi-n3LrgDZF-xRjPhefLxDYOhpTrYSJ5kAog9CJTgWInD1zXVGTtMab8F7GfvtmEBtks99JscF1skBQBqG9NQDDbyZZ1SnDDbS4_gReo0C3RC3fsIcDNHc0cZ1AkYnQQPukf6ikkKEsJRpOjATqg4PzbZgO8F_gLK3cTz5Oq0Tli4WRwWSMWQFvw24dHWYt8YD474fQ2GriL3lTemAf53r7UiNOie2cpW2VtUqWm_x-q-1Iz4DcgZfepHnH2GXkpH4IwxmHREMXO4dS74CvJifFAfH57-qXgGlZ0sPQQebk9iFornGoVqXR1Gm7AWbQ_Ne55QmKIF8BI2ubSkX0F76dVrWA9jJg2wGmGj4b3BTOc9KbgQAtuKPyluZR97qLC-IU8aBTarKA2yOQMdc7s3QcU1B-mQKmJ8eb-5Qt4yMg1ayl7roETStjh1oiDACA5RZyO-CaUK7LLwG3OpLrMllCR0yk_2n8G3aCfxauRAblIboj3bpcq56ddyXgFeLeOedohWMec9AEKB-Tt4Ovxv_PFy1uG6TBt-5HN-7_EgxKJ6iPklgiH3cFpG0FpGJXI7fT": {"documentURL": "http://www.adf.ly/", "parent": "http://www.adf.ly/", "url": "http://www.google.com/recaptcha/api/image?c=03AHJ_VusklXo3i4W1oVTV1_T7HfXCrtYSaTgY-TIJ2Rg-stiGU84z7wHlJKAE77gtTi443xpW20DKvHCFyo379t2SSSEsqZJOQXE0_5CtAoDuyk6I0vX_wG2nv_RoTm8RPgSYN5_xqP6hWEPohFplMKr8dvkKKnJbG3iLuqZYsFK6TkEMuUjnJISB6XLFU3zWfAGripVG0zFNMwELiotY8UtCvvjo8sMSnQ&th=,BfRX9NWweSjAM18tQ1a2tP-YFW-TcMTwAAAB6aAAAAS3awNj-xaxzfabbDAdRoS7PcfEJwaR7m5BEvu0Nm6eIst4ymEJkUcGyq8n4JwPptd-wjWVnlJEyA-tZPm8YzdhgLHjfhGUususM7Qh1SovD36nt8rpdzvSRiznoTNKdNiU1974mvG8hYI7mGXwavi73NW3idPuBf94M22eO_2o0atqdq7ERZoBbHxhe_qAI7FFGABePXUjoE4qy6q6bSwaNlSLQixu7jKxg7d2EAtuRcRLUeXashObkK-_p2dYBBfzTf_h_4-q2P7maqTzSamPVJEZcWfK81o7qBpgS74qeRPhM0CvulRatUHSpz4PBXG1y9LfvDw8g2bzKDMbSIzDT0GxJ6vYku8ldwd3RGCR9zQrLmsNBoUDcNB3Bfd6z4TZb0C_rYhT2wst1W70deoR7Fnwg3zKPT_91fuDT7HKW4JUjpSUotr0Bl0QWS8ihESyb05DlgXzFZRz_ZXdwB1IqRVG_tclx6J5JvylXftnTtIv8GMhTrjtZoEmRAwlgpu3IZxu7u01S5pLQoJGhxVuHahrIP17oHeTCt11UES3Z0H3kEHs5eS1mn6UeLs6ZSI9MeeHFyi-n3LrgDZF-xRjPhefLxDYOhpTrYSJ5kAog9CJTgWInD1zXVGTtMab8F7GfvtmEBtks99JscF1skBQBqG9NQDDbyZZ1SnDDbS4_gReo0C3RC3fsIcDNHc0cZ1AkYnQQPukf6ikkKEsJRpOjATqg4PzbZgO8F_gLK3cTz5Oq0Tli4WRwWSMWQFvw24dHWYt8YD474fQ2GriL3lTemAf53r7UiNOie2cpW2VtUqWm_x-q-1Iz4DcgZfepHnH2GXkpH4IwxmHREMXO4dS74CvJifFAfH57-qXgGlZ0sPQQebk9iFornGoVqXR1Gm7AWbQ_Ne55QmKIF8BI2ubSkX0F76dVrWA9jJg2wGmGj4b3BTOc9KbgQAtuKPyluZR97qLC-IU8aBTarKA2yOQMdc7s3QcU1B-mQKmJ8eb-5Qt4yMg1ayl7roETStjh1oiDACA5RZyO-CaUK7LLwG3OpLrMllCR0yk_2n8G3aCfxauRAblIboj3bpcq56ddyXgFeLeOedohWMec9AEKB-Tt4Ovxv_PFy1uG6TBt-5HN-7_EgxKJ6iPklgiH3cFpG0FpGJXI7fT", "isRoot": false, "priority": "Low", "found_index": 84, "request_id": "5550.120", "type": "Image", "children": [], "isLeaf": true}, "http://cdn.adf.ly/static/image/language_flags.png": {"documentURL": "http://www.adf.ly/", "parent": "http://cdn.adf.ly/static/css/core46.css", "url": "http://cdn.adf.ly/static/image/language_flags.png", "isRoot": false, "priority": "Low", "found_index": 32, "request_id": "5550.54", "type": "Image", "children": [], "isLeaf": true}, "http://www.google.com/recaptcha/api/js/recaptcha.js": {"isRoot": false, "parent": "http://www.google.com/recaptcha/api/challenge?k=6LcmBQUTAAAAABRUqaI7Jt-bv9vr4Xpwh7MMVVW5", "url": "http://www.google.com/recaptcha/api/js/recaptcha.js", "priority": "High", "found_index": 60, "request_id": "5550.85", "type": "Script", "children": ["http://www.google.com/js/th/Uagp0-muJQIDIZscZPeJ3RryBE4i-S2r9ivzwT9G39o.js", "http://www.google.com/recaptcha/api/reload?c=03AHJ_VusivURfPEBJ4k-MHVHZx3hUJPm5uwdZZ-6mOeT-lsnz6gnhZ8jP3nODtrXBgSC8tS1tIyKmcvEDroa5NgzQ7e1cvdz0-CWySJqT4d08XKgfY36flE-sccmBJTEqUDDtu9qkGWpD-KE3w2NRPKLIaozTEEKYxkOyoxN0PfwcWsM4KhMVf8UaielSgBfznwY7zRKftsSD&k=6LcmBQUTAAAAABRUqaI7Jt-bv9vr4Xpwh7MMVVW5&reason=i&type=image&lang=en&th=,BPVX9dSweSjAM18tQ1a2tP-YFW-TcMTwAAABZKAAAARyawNjCVwC85U2ioewatMCFlJCSthtevX9udZvGKL3ULaVaWzpE3QvvGDnYUhj_lQHyPCpQrOJ-zvN225EDt5puPe_nGrt5BOFj_9FyUgQb9yeNlR0jXY9PPJ-0-Go3rFJBKId2GRKgGTddZ_kOUVD7evBMpls1mwv-PCKjmtfvfZrJRrh6RNuUpA6xHcFhvDpXkJKgXHiNoaVcpPDVTa3cD1P1BM2Hp8xl7uKQtTBGT6guNrAn3ML6llXDyeSpZwI9QpbLUXoJHV8uZy3F7xUeGikNgiKWnFm-cig_wSdCvrBO55AoRfsI3i5afXyTLr7DG79xXtAlxhImV6U1WMDVj_VIOAozunWMxYjVoebAXApNIQd_uJvIdDN678WUqdb7RfJhnvA5z2l56jsvvWFbpPmE41jSfiwHT3qGrbs3eLj-hhgYHUMFI4jzMyHr3cb4_yPG-28uNSVSxhz79ZoWjj-GBbbKpjTnsGZjeQtdCgFfze-zTnDJ4GbcjkicQ-rUjbj2BWSd86q0LuNjMGZV8f9A6yO6arLTcfh_rJTYY2BunDusGuD9BiN05dUwqBFssOErh1BpOXUrM8Dv__IqvCBxQ-FsQEuFTjVmJ3F_CHZjFgRV3Qs8uPqC0CrboM97a-A2s4RHAM1kwMchxSujiwWtK0Kq1_lrbFOv8-2f-xcZGcb41dN1JDpE3l7sIiP0IWoG8XhgaE676B6JFUrrzOMlSWXjqycZvyA5eATClOCm54T7-2dt63fpSYCEAl3GSmKBc_iOhlx7Eha94LvuNeGH5dTJ246_cZMIadpT8I_kD9wvGkEnom_pKGRZqOircHCcN21eioJ31xyZ8ouzyrxGzchP3o0rJ3hGz5PWHr_GsZKtwv_BuSHerrVOlTXTrSbialTs0yID-sxAcPBGuR9eUWEtRDiS2BTw714So11tJsIQdP5Xs10z0lGub822QVZIkx-kQ8MHEMonyc3DPs1sHpl22VTZC-5or2azhLsgAyp2bJxzEAQVWFkyhsBOLfc8XC5VtshPKZfvxLXo6I7r7CSkDdpfjQZQVA8MGTU3F_has7Ft3DKUwvssLFHpLJ-06apaYBE2lcHnM_7okBCrWBVqIskQsh-wcUeJZZIlQTSIzYCZyu7U5HBUN-DpzJhHsER"], "isLeaf": false, "documentURL": "http://www.adf.ly/"}, "http://cdn.adf.ly/static/js/modernizr.js": {"documentURL": "http://www.adf.ly/", "parent": "http://www.adf.ly/", "url": "http://cdn.adf.ly/static/js/modernizr.js", "isRoot": false, "priority": "High", "found_index": 13, "request_id": "5550.13", "type": "Script", "children": [], "isLeaf": true}, "http://s7.addthis.com/static/sh_mobile.92bb263c60d77a822f41d4b0.html": {"documentURL": "http://s7.addthis.com/static/sh_mobile.92bb263c60d77a822f41d4b0.html", "parent": "http://s7.addthis.com/js/300/addthis_widget.js", "url": "http://s7.addthis.com/static/sh_mobile.92bb263c60d77a822f41d4b0.html", "isRoot": false, "priority": "VeryLow", "found_index": 73, "request_id": "5550.103", "type": "Document", "children": [], "isLeaf": true}, "http://www.google.com/js/th/Uagp0-muJQIDIZscZPeJ3RryBE4i-S2r9ivzwT9G39o.js": {"documentURL": "http://www.adf.ly/", "parent": "http://www.google.com/recaptcha/api/js/recaptcha.js", "url": "http://www.google.com/js/th/Uagp0-muJQIDIZscZPeJ3RryBE4i-S2r9ivzwT9G39o.js", "isRoot": false, "priority": "Low", "found_index": 64, "request_id": "5550.90", "type": "Script", "children": [], "isLeaf": true}, "https://js-agent.newrelic.com/nr-998.min.js": {"isRoot": false, "parent": "http://www.adf.ly/", "url": "https://js-agent.newrelic.com/nr-998.min.js", "priority": "Low", "found_index": 94, "request_id": "5550.139", "type": "Script", "children": ["https://bam.nr-data.net/1/92a411bc23?a=2344943,2334836&v=998.365d633&to=YlNSbUYAV0IFBhdaWVsZc0xHFVZcSwwNV1NNdV9XQBNWXQgAERxfW1JVQQ%3D%3D&rst=12720&ref=http://www.adf.ly/&ap=24&be=408&fe=11990&dc=2421&af=err,xhr&perf=%7B%22timing%22:%7B%22of%22:1496541609816,%22n%22:0,%22f%22:2,%22dn%22:2,%22dne%22:2,%22c%22:2,%22ce%22:2,%22rq%22:27,%22rp%22:212,%22rpe%22:375,%22dl%22:304,%22di%22:2829,%22ds%22:2829,%22de%22:3279,%22dc%22:12395,%22l%22:12397,%22le%22:12404%7D,%22navigation%22:%7B%7D%7D&at=ThRRGw4aREw%3D&jsonp=NREUM.setToken"], "isLeaf": false, "documentURL": "http://www.adf.ly/"}, "http://cdn.adf.ly/static/js/jquery-1.7.1.min.js": {"isRoot": false, "parent": "http://www.adf.ly/", "url": "http://cdn.adf.ly/static/js/jquery-1.7.1.min.js", "priority": "High", "found_index": 5, "request_id": "5550.5", "type": "Script", "children": ["http://www.google.com/recaptcha/api/challenge?k=6LcmBQUTAAAAABRUqaI7Jt-bv9vr4Xpwh7MMVVW5&_=1496541612851", "http://cdn.adf.ly/static/image/chosen-sprite.png", "http://cdn.adf.ly/static/css/jquery-ui/ui-lightness/images/ui-bg_highlight-soft_100_eeeeee_1x100.png", "http://www.google.com/recaptcha/api/js/recaptcha.js?_=1496541612855"], "isLeaf": false, "documentURL": "http://www.adf.ly/"}, "http://platform.linkedin.com/in.js": {"isRoot": false, "parent": "http://www.adf.ly/", "url": "http://platform.linkedin.com/in.js", "priority": "Medium", "found_index": 23, "request_id": "5550.23", "type": "Script", "children": ["https://platform.linkedin.com/js/secureAnonymousFramework?v=0.0.2000-RC8.59768-1429&lang=en_US"], "isLeaf": false, "documentURL": "http://www.adf.ly/"}, "http://s7.addthis.com/js/300/addthis_widget.js": {"isRoot": false, "parent": "http://www.adf.ly/", "url": "http://s7.addthis.com/js/300/addthis_widget.js", "priority": "Medium", "found_index": 22, "request_id": "5550.22", "type": "Script", "children": ["http://s7.addthis.com/static/layers.ea0ccaf667d08a14f4c7.js", "http://m.addthis.com/live/red_lojson/300lo.json?si=593369ab2efd622a&bkl=0&bl=1&pdt=361&sid=593369ab2efd622a&pub=ra-53993a6f0d2e8c74&rev=v7.9.5-wp&ln=en&pc=men&cb=0&ab=-&dp=www.adf.ly&fp=&fr=&of=0&pd=0&irt=1&vcl=1&md=0&ct=1&tct=0&abt=0&cdn=0&pi=1&rb=0&gen=100&chr=UTF-8&mk=adfly%2Cadf.ly%2Cshort%20links%2Ctinyurl%2Cbitly%2Cbit.ly%2Cearn%20money%2Clink%20advertising%2Ctiny%20url%2Curl%20shortener&colc=1496541612989&jsl=161&uvs=5933697a9703ad54002&skipb=1&callback=addthis.cbs.oln9_118435636894462790", "http://s7.addthis.com/static/sh_mobile.92bb263c60d77a822f41d4b0.html", "http://m.addthisedge.com/live/boost/ra-53993a6f0d2e8c74/_ate.track.config_resp"], "isLeaf": false, "documentURL": "http://www.adf.ly/"}, "http://cdn.adf.ly/static/image/api.png": {"documentURL": "http://www.adf.ly/", "parent": "http://cdn.adf.ly/static/css/core46.css", "url": "http://cdn.adf.ly/static/image/api.png", "isRoot": false, "priority": "Low", "found_index": 47, "request_id": "5550.69", "type": "Image", "children": [], "isLeaf": true}, "http://m.addthisedge.com/live/boost/ra-53993a6f0d2e8c74/_ate.track.config_resp": {"documentURL": "http://www.adf.ly/", "parent": "http://s7.addthis.com/js/300/addthis_widget.js", "url": "http://m.addthisedge.com/live/boost/ra-53993a6f0d2e8c74/_ate.track.config_resp", "isRoot": false, "priority": "Low", "found_index": 71, "request_id": "5550.101", "type": "Script", "children": [], "isLeaf": true}, "http://cdn.adf.ly/static/image/ads.png": {"documentURL": "http://www.adf.ly/", "parent": "http://cdn.adf.ly/static/css/core46.css", "url": "http://cdn.adf.ly/static/image/ads.png", "isRoot": false, "priority": "Low", "found_index": 44, "request_id": "5550.66", "type": "Image", "children": [], "isLeaf": true}, "http://cdn.adf.ly/static/image/header_gradient.jpg": {"documentURL": "http://www.adf.ly/", "parent": "http://cdn.adf.ly/static/css/core46.css", "url": "http://cdn.adf.ly/static/image/header_gradient.jpg", "isRoot": false, "priority": "Low", "found_index": 29, "request_id": "5550.51", "type": "Image", "children": [], "isLeaf": true}, "http://cdn.adf.ly/static/image/footer_home_ll_bg.png": {"documentURL": "http://www.adf.ly/", "parent": "http://cdn.adf.ly/static/css/core46.css", "url": "http://cdn.adf.ly/static/image/footer_home_ll_bg.png", "isRoot": false, "priority": "Low", "found_index": 56, "request_id": "5550.79", "type": "Image", "children": [], "isLeaf": true}, "http://cdn.adf.ly/static/image/ft_alertpay.png": {"documentURL": "http://www.adf.ly/", "parent": "http://cdn.adf.ly/static/css/core46.css", "url": "http://cdn.adf.ly/static/image/ft_alertpay.png", "isRoot": false, "priority": "Low", "found_index": 59, "request_id": "5550.83", "type": "Image", "children": [], "isLeaf": true}, "http://cdn.adf.ly/static/css/jquery-ui/ui-lightness/images/ui-bg_gloss-wave_35_f6a828_500x100.png": {"documentURL": "http://www.adf.ly/", "parent": "http://cdn.adf.ly/static/js/spin.js", "url": "http://cdn.adf.ly/static/css/jquery-ui/ui-lightness/images/ui-bg_gloss-wave_35_f6a828_500x100.png", "isRoot": false, "priority": "Low", "found_index": 67, "request_id": "5550.97", "type": "Image", "children": [], "isLeaf": true}, "https://static.licdn.com/scds/concat/common/js?h=b04y4p1rkdv631n988yzucz8q": {"documentURL": "https://www.linkedin.com/cws/followcompany?companyIdentifier=5359353&counterPosition=none&original_referer=http%3A%2F%2Fwww.adf.ly%2F&token=&isFramed=false&lang=en_US&_ts=1496541619861.3257&xd_origin_host=http%3A%2F%2Fwww.adf.ly", "parent": "https://www.linkedin.com/cws/followcompany?companyIdentifier=5359353&counterPosition=none&original_referer=http%3A%2F%2Fwww.adf.ly%2F&token=&isFramed=false&lang=en_US&_ts=1496541619861.3257&xd_origin_host=http%3A%2F%2Fwww.adf.ly", "url": "https://static.licdn.com/scds/concat/common/js?h=b04y4p1rkdv631n988yzucz8q", "isRoot": false, "priority": "VeryLow", "found_index": 92, "request_id": "5550.128", "type": "Script", "children": [], "isLeaf": true}, "http://cdn.adf.ly/static/js/jquery.browserdetect.min.js": {"documentURL": "http://www.adf.ly/", "parent": "http://www.adf.ly/", "url": "http://cdn.adf.ly/static/js/jquery.browserdetect.min.js", "isRoot": false, "priority": "High", "found_index": 6, "request_id": "5550.6", "type": "Script", "children": [], "isLeaf": true}, "https://staticxx.facebook.com/connect/xd_arbiter/r/D6ZfFsLEB4F.js?version=42": {"documentURL": "https://staticxx.facebook.com/connect/xd_arbiter/r/D6ZfFsLEB4F.js?version=42", "parent": "http://connect.facebook.net/en_US/sdk.js", "url": "https://staticxx.facebook.com/connect/xd_arbiter/r/D6ZfFsLEB4F.js?version=42", "isRoot": false, "priority": "VeryLow", "found_index": 63, "request_id": "5550.89", "type": "Document", "children": [], "isLeaf": true}, "http://www.google.com/recaptcha/api/img/red/refresh.gif": {"documentURL": "http://www.adf.ly/", "parent": "http://www.adf.ly/", "url": "http://www.google.com/recaptcha/api/img/red/refresh.gif", "isRoot": false, "priority": "Low", "found_index": 75, "request_id": "5550.105", "type": "Image", "children": [], "isLeaf": true}, "http://cdn.adf.ly/static/js/ZeroClipboard.js": {"documentURL": "http://www.adf.ly/", "parent": "http://www.adf.ly/", "url": "http://cdn.adf.ly/static/js/ZeroClipboard.js", "isRoot": false, "priority": "High", "found_index": 12, "request_id": "5550.12", "type": "Script", "children": [], "isLeaf": true}, "http://connect.facebook.net/en_US/sdk.js": {"isRoot": false, "parent": "http://www.adf.ly/", "url": "http://connect.facebook.net/en_US/sdk.js", "priority": "Low", "found_index": 27, "request_id": "5550.45", "type": "Script", "children": ["http://staticxx.facebook.com/connect/xd_arbiter/r/D6ZfFsLEB4F.js?version=42", "https://staticxx.facebook.com/connect/xd_arbiter/r/D6ZfFsLEB4F.js?version=42", "https://www.facebook.com/v2.0/plugins/like.php?action=like&app_id=399141353502152&channel=http%3A%2F%2Fstaticxx.facebook.com%2Fconnect%2Fxd_arbiter%2Fr%2FD6ZfFsLEB4F.js%3Fversion%3D42%23cb%3Df2e1767fdd9b89%26domain%3Dwww.adf.ly%26origin%3Dhttp%253A%252F%252Fwww.adf.ly%252Ff9943e9dc72f28%26relation%3Dparent.parent&container_width=0&href=https%3A%2F%2Fwww.facebook.com%2FFB_SLUG&layout=standard&locale=en_US&sdk=joey&share=true&show_faces=true&width=280"], "isLeaf": false, "documentURL": "http://www.adf.ly/"}, "http://cdn.adf.ly/static/js/jquery.ulightbox.js": {"documentURL": "http://www.adf.ly/", "parent": "http://www.adf.ly/", "url": "http://cdn.adf.ly/static/js/jquery.ulightbox.js", "isRoot": false, "priority": "High", "found_index": 18, "request_id": "5550.18", "type": "Script", "children": [], "isLeaf": true}, "http://cdn.adf.ly/static/image/delete2.png": {"documentURL": "http://www.adf.ly/", "parent": "http://www.adf.ly/", "url": "http://cdn.adf.ly/static/image/delete2.png", "isRoot": false, "priority": "Low", "found_index": 26, "request_id": "5550.30", "type": "Image", "children": [], "isLeaf": true}}